[
  {
    "lawd_cd": "11215",
    "deal_ymd": "202301",
    "total_count": 12,
    "items": [
      {
        "sggCd": "11215",
        "sggNm": "광진구",
        "umdNm": "중곡동",
        "jimok": "도로",
        "jibun": "1**",
        "dealAmount": "2,363",
        "dealArea": "6.97",
        "dealingGbn": "직거래",
        "landUse": "제2종일반주거지역",
        "shareDealingType": "지분",
        "cdealType": null,
        "cdealDay": null,
        "estateAgentSggNm": null,
        "dealYear": "2023",
        "dealMonth": "1",
        "dealDay": "9"
      },
      {
        "sggCd": "11215",
        "sggNm": "광진구",
        "umdNm": "구의동",
        "jimok": "도로",
        "jibun": "2**",
        "dealAmount": "1,500",
        "dealArea": "3.31",
        "dealingGbn": "직거래",
        "landUse": "제2종일반주거지역",
        "shareDealingType": "지분",
        "cdealType": null,
        "cdealDay": null,
        "estateAgentSggNm": null,
        "dealYear": "2023",
        "dealMonth": "1",
        "dealDay": "31"
      },
      {
        "sggCd": "11215",
        "sggNm": "광진구",
        "umdNm": "중곡동",
        "jimok": "도로",
        "jibun": "1**",
        "dealAmount": "3,051",
        "dealArea": "9",
        "dealingGbn": "직거래",
        "landUse": "제2종일반주거지역",
        "shareDealingType": "지분",
        "cdealType": null,
        "cdealDay": null,
        "estateAgentSggNm": null,
        "dealYear": "2023",
        "dealMonth": "1",
        "dealDay": "9"
      },
      {
        "sggCd": "11215",
        "sggNm": "광진구",
        "umdNm": "중곡동",
        "jimok": "도로",
        "jibun": "1**",
        "dealAmount": "890",
        "dealArea": "3.31",
        "dealingGbn": "직거래",
        "landUse": "제2종일반주거지역",
        "shareDealingType": "지분",
        "cdealType": null,
        "cdealDay": null,
        "estateAgentSggNm": null,
        "dealYear": "2023",
        "dealMonth": "1",
        "dealDay": "9"
      },
      {
        "sggCd": "11215",
        "sggNm": "광진구",
        "umdNm": "중곡동",
        "jimok": "도로",
        "jibun": "1**",
        "dealAmount": "890",
        "dealArea": "3.31",
        "dealingGbn": "직거래",
        "landUse": "제2종일반주거지역",
        "shareDealingType": "지분",
        "cdealType": null,
        "cdealDay": null,
        "estateAgentSggNm": null,
        "dealYear": "2023",
        "dealMonth": "1",
        "dealDay": "18"
      },
      {
        "sggCd": "11215",
        "sggNm": "광진구",
        "umdNm": "중곡동",
        "jimok": "도로",
        "jibun": "1**",
        "dealAmount": "890",
        "dealArea": "3.31",
        "dealingGbn": "직거래",
        "landUse": "제2종일반주거지역",
        "shareDealingType": "지분",
        "cdealType": null,
        "cdealDay": null,
        "estateAgentSggNm": null,
        "dealYear": "2023",
        "dealMonth": "1",
        "dealDay": "31"
      },
      {
        "sggCd": "11215",
        "sggNm": "광진구",
        "umdNm": "중곡동",
        "jimok": "도로",
        "jibun": "1**",
        "dealAmount": "890",
        "dealArea": "3.31",
        "dealingGbn": "직거래",
        "landUse": "제2종일반주거지역",
        "shareDealingType": "지분",
        "cdealType": null,
        "cdealDay": null,
        "estateAgentSggNm": null,
        "dealYear": "2023",
        "dealMonth": "1",
        "dealDay": "6"
      },
      {
        "sggCd": "11215",
        "sggNm": "광진구",
        "umdNm": "중곡동",
        "jimok": "도로",
        "jibun": "1**",
        "dealAmount": "2,670",
        "dealArea": "9.92",
        "dealingGbn": "직거래",
        "landUse": "제2종일반주거지역",
        "shareDealingType": "지분",
        "cdealType": null,
        "cdealDay": null,
        "estateAgentSggNm": null,
        "dealYear": "2023",
        "dealMonth": "1",
        "dealDay": "30"
      },
      {
        "sggCd": "11215",
        "sggNm": "광진구",
        "umdNm": "중곡동",
        "jimok": "도로",
        "jibun": "1**",
        "dealAmount": "2,034",
        "dealArea": "6",
        "dealingGbn": "직거래",
        "landUse": "제2종일반주거지역",
        "shareDealingType": "지분",
        "cdealType": null,
        "cdealDay": null,
        "estateAgentSggNm": null,
        "dealYear": "2023",
        "dealMonth": "1",
        "dealDay": "6"
      },
      {
        "sggCd": "11215",
        "sggNm": "광진구",
        "umdNm": "중곡동",
        "jimok": "도로",
        "jibun": "1**",
        "dealAmount": "1,695",
        "dealArea": "5",
        "dealingGbn": "직거래",
        "landUse": "제2종일반주거지역",
        "shareDealingType": "지분",
        "cdealType": null,
        "cdealDay": null,
        "estateAgentSggNm": null,
        "dealYear": "2023",
        "dealMonth": "1",
        "dealDay": "5"
      },
      {
        "sggCd": "11215",
        "sggNm": "광진구",
        "umdNm": "중곡동",
        "jimok": "도로",
        "jibun": "1**",
        "dealAmount": "2,712",
        "dealArea": "8",
        "dealingGbn": "직거래",
        "landUse": "제2종일반주거지역",
        "shareDealingType": "지분",
        "cdealType": null,
        "cdealDay": null,
        "estateAgentSggNm": null,
        "dealYear": "2023",
        "dealMonth": "1",
        "dealDay": "5"
      },
      {
        "sggCd": "11215",
        "sggNm": "광진구",
        "umdNm": "중곡동",
        "jimok": "도로",
        "jibun": "1**",
        "dealAmount": "2,765",
        "dealArea": "7",
        "dealingGbn": "직거래",
        "landUse": "제2종일반주거지역",
        "shareDealingType": "지분",
        "cdealType": null,
        "cdealDay": null,
        "estateAgentSggNm": null,
        "dealYear": "2023",
        "dealMonth": "1",
        "dealDay": "5"
      }
    ]
  },
  {
    "lawd_cd": "11215",
    "deal_ymd": "202302",
    "total_count": 5,
    "items": [
      {
        "sggCd": "11215",
        "sggNm": "광진구",
        "umdNm": "중곡동",
        "jimok": "도로",
        "jibun": "7*",
        "dealAmount": "100",
        "dealArea": "4.6",
        "dealingGbn": "중개거래",
        "landUse": "제1종일반주거지역",
        "shareDealingType": null,
        "cdealType": null,
        "cdealDay": null,
        "estateAgentSggNm": "서울 광진구",
        "dealYear": "2023",
        "dealMonth": "2",
        "dealDay": "7"
      },
      {
        "sggCd": "11215",
        "sggNm": "광진구",
        "umdNm": "중곡동",
        "jimok": "도로",
        "jibun": "1**",
        "dealAmount": "1,695",
        "dealArea": "5",
        "dealingGbn": "직거래",
        "landUse": "제2종일반주거지역",
        "shareDealingType": "지분",
        "cdealType": null,
        "cdealDay": null,
        "estateAgentSggNm": null,
        "dealYear": "2023",
        "dealMonth": "2",
        "dealDay": "10"
      },
      {
        "sggCd": "11215",
        "sggNm": "광진구",
        "umdNm": "중곡동",
        "jimok": "도로",
        "jibun": "1**",
        "dealAmount": "1,017",
        "dealArea": "3",
        "dealingGbn": "직거래",
        "landUse": "제2종일반주거지역",
        "shareDealingType": "지분",
        "cdealType": null,
        "cdealDay": null,
        "estateAgentSggNm": null,
        "dealYear": "2023",
        "dealMonth": "2",
        "dealDay": "14"
      },
      {
        "sggCd": "11215",
        "sggNm": "광진구",
        "umdNm": "중곡동",
        "jimok": "도로",
        "jibun": "1**",
        "dealAmount": "890",
        "dealArea": "3.31",
        "dealingGbn": "직거래",
        "landUse": "제2종일반주거지역",
        "shareDealingType": "지분",
        "cdealType": null,
        "cdealDay": null,
        "estateAgentSggNm": null,
        "dealYear": "2023",
        "dealMonth": "2",
        "dealDay": "3"
      },
      {
        "sggCd": "11215",
        "sggNm": "광진구",
        "umdNm": "자양동",
        "jimok": "도로",
        "jibun": "6**",
        "dealAmount": "600",
        "dealArea": "1.95",
        "dealingGbn": "직거래",
        "landUse": "제2종일반주거지역",
        "shareDealingType": "지분",
        "cdealType": null,
        "cdealDay": null,
        "estateAgentSggNm": null,
        "dealYear": "2023",
        "dealMonth": "2",
        "dealDay": "7"
      }
    ]
  },
  {
    "lawd_cd": "11215",
    "deal_ymd": "202303",
    "total_count": 8,
    "items": [
      {
        "sggCd": "11215",
        "sggNm": "광진구",
        "umdNm": "자양동",
        "jimok": "대",
        "jibun": "1*",
        "dealAmount": "450,000",
        "dealArea": "329.9",
        "dealingGbn": "중개거래",
        "landUse": "제2종일반주거지역",
        "shareDealingType": null,
        "cdealType": null,
        "cdealDay": null,
        "estateAgentSggNm": "서울 광진구",
        "dealYear": "2023",
        "dealMonth": "3",
        "dealDay": "31"
      },
      {
        "sggCd": "11215",
        "sggNm": "광진구",
        "umdNm": "화양동",
        "jimok": "대",
        "jibun": "3*",
        "dealAmount": "107,700",
        "dealArea": "104.8",
        "dealingGbn": "중개거래",
        "landUse": "제2종일반주거지역",
        "shareDealingType": null,
        "cdealType": null,
        "cdealDay": null,
        "estateAgentSggNm": "서울 용산구",
        "dealYear": "2023",
        "dealMonth": "3",
        "dealDay": "30"
      },
      {
        "sggCd": "11215",
        "sggNm": "광진구",
        "umdNm": "화양동",
        "jimok": "대",
        "jibun": "3*",
        "dealAmount": "144,700",
        "dealArea": "165",
        "dealingGbn": "중개거래",
        "landUse": "제2종일반주거지역",
        "shareDealingType": null,
        "cdealType": null,
        "cdealDay": null,
        "estateAgentSggNm": "서울 용산구",
        "dealYear": "2023",
        "dealMonth": "3",
        "dealDay": "30"
      },
      {
        "sggCd": "11215",
        "sggNm": "광진구",
        "umdNm": "구의동",
        "jimok": "도로",
        "jibun": "2**",
        "dealAmount": "1,360",
        "dealArea": "3.31",
        "dealingGbn": "직거래",
        "landUse": "제2종일반주거지역",
        "shareDealingType": "지분",
        "cdealType": null,
        "cdealDay": null,
        "estateAgentSggNm": null,
        "dealYear": "2023",
        "dealMonth": "3",
        "dealDay": "31"
      },
      {
        "sggCd": "11215",
        "sggNm": "광진구",
        "umdNm": "구의동",
        "jimok": "도로",
        "jibun": "2**",
        "dealAmount": "1,360",
        "dealArea": "3.31",
        "dealingGbn": "직거래",
        "landUse": "제2종일반주거지역",
        "shareDealingType": "지분",
        "cdealType": null,
        "cdealDay": null,
        "estateAgentSggNm": null,
        "dealYear": "2023",
        "dealMonth": "3",
        "dealDay": "30"
      },
      {
        "sggCd": "11215",
        "sggNm": "광진구",
        "umdNm": "구의동",
        "jimok": "도로",
        "jibun": "2**",
        "dealAmount": "2,720",
        "dealArea": "6.61",
        "dealingGbn": "직거래",
        "landUse": "제2종일반주거지역",
        "shareDealingType": "지분",
        "cdealType": null,
        "cdealDay": null,
        "estateAgentSggNm": null,
        "dealYear": "2023",
        "dealMonth": "3",
        "dealDay": "28"
      },
      {
        "sggCd": "11215",
        "sggNm": "광진구",
        "umdNm": "중곡동",
        "jimok": "대",
        "jibun": "9*",
        "dealAmount": "78,300",
        "dealArea": "69.8",
        "dealingGbn": "직거래",
        "landUse": "제3종일반주거지역",
        "shareDealingType": null,
        "cdealType": null,
        "cdealDay": null,
        "estateAgentSggNm": null,
        "dealYear": "2023",
        "dealMonth": "3",
        "dealDay": "6"
      },
      {
        "sggCd": "11215",
        "sggNm": "광진구",
        "umdNm": "구의동",
        "jimok": "도로",
        "jibun": "2**",
        "dealAmount": "4,170",
        "dealArea": "24.45",
        "dealingGbn": "직거래",
        "landUse": "제2종일반주거지역",
        "shareDealingType": "지분",
        "cdealType": null,
        "cdealDay": null,
        "estateAgentSggNm": null,
        "dealYear": "2023",
        "dealMonth": "3",
        "dealDay": "1"
      }
    ]
  },
  {
    "lawd_cd": "11215",
    "deal_ymd": "202304",
    "total_count": 7,
    "items": [
      {
        "sggCd": "11215",
        "sggNm": "광진구",
        "umdNm": "구의동",
        "jimok": "대",
        "jibun": "2**",
        "dealAmount": "130,400",
        "dealArea": "107.8",
        "dealingGbn": "중개거래",
        "landUse": "제3종일반주거지역",
        "shareDealingType": null,
        "cdealType": null,
        "cdealDay": null,
        "estateAgentSggNm": "서울 광진구",
        "dealYear": "2023",
        "dealMonth": "4",
        "dealDay": "28"
      },
      {
        "sggCd": "11215",
        "sggNm": "광진구",
        "umdNm": "구의동",
        "jimok": "도로",
        "jibun": "2**",
        "dealAmount": "4,620",
        "dealArea": "27.09",
        "dealingGbn": "직거래",
        "landUse": "제2종일반주거지역",
        "shareDealingType": "지분",
        "cdealType": null,
        "cdealDay": null,
        "estateAgentSggNm": null,
        "dealYear": "2023",
        "dealMonth": "4",
        "dealDay": "27"
      },
      {
        "sggCd": "11215",
        "sggNm": "광진구",
        "umdNm": "구의동",
        "jimok": "도로",
        "jibun": "2**",
        "dealAmount": "3,078",
        "dealArea": "18.06",
        "dealingGbn": "직거래",
        "landUse": "제2종일반주거지역",
        "shareDealingType": "지분",
        "cdealType": null,
        "cdealDay": null,
        "estateAgentSggNm": null,
        "dealYear": "2023",
        "dealMonth": "4",
        "dealDay": "27"
      },
      {
        "sggCd": "11215",
        "sggNm": "광진구",
        "umdNm": "구의동",
        "jimok": "도로",
        "jibun": "2**",
        "dealAmount": "15,000",
        "dealArea": "33.06",
        "dealingGbn": "직거래",
        "landUse": "제2종일반주거지역",
        "shareDealingType": "지분",
        "cdealType": null,
        "cdealDay": null,
        "estateAgentSggNm": null,
        "dealYear": "2023",
        "dealMonth": "4",
        "dealDay": "27"
      },
      {
        "sggCd": "11215",
        "sggNm": "광진구",
        "umdNm": "광장동",
        "jimok": "임야",
        "jibun": "2**",
        "dealAmount": "27,000",
        "dealArea": "19",
        "dealingGbn": "직거래",
        "landUse": "제3종일반주거지역",
        "shareDealingType": null,
        "cdealType": null,
        "cdealDay": null,
        "estateAgentSggNm": null,
        "dealYear": "2023",
        "dealMonth": "4",
        "dealDay": "11"
      },
      {
        "sggCd": "11215",
        "sggNm": "광진구",
        "umdNm": "구의동",
        "jimok": "도로",
        "jibun": "2**",
        "dealAmount": "2,720",
        "dealArea": "6.61",
        "dealingGbn": "직거래",
        "landUse": "제2종일반주거지역",
        "shareDealingType": "지분",
        "cdealType": null,
        "cdealDay": null,
        "estateAgentSggNm": null,
        "dealYear": "2023",
        "dealMonth": "4",
        "dealDay": "1"
      },
      {
        "sggCd": "11215",
        "sggNm": "광진구",
        "umdNm": "자양동",
        "jimok": "대",
        "jibun": "6**",
        "dealAmount": "109,000",
        "dealArea": "198.3",
        "dealingGbn": "직거래",
        "landUse": "제2종일반주거지역",
        "shareDealingType": null,
        "cdealType": null,
        "cdealDay": null,
        "estateAgentSggNm": null,
        "dealYear": "2023",
        "dealMonth": "4",
        "dealDay": "7"
      }
    ]
  },
  {
    "lawd_cd": "11215",
    "deal_ymd": "202305",
    "total_count": 59,
    "items": [
      {
        "sggCd": "11215",
        "sggNm": "광진구",
        "umdNm": "자양동",
        "jimok": "도로",
        "jibun": "8*",
        "dealAmount": "953",
        "dealArea": "1.5",
        "dealingGbn": "직거래",
        "landUse": "제2종일반주거지역",
        "shareDealingType": "지분",
        "cdealType": null,
        "cdealDay": null,
        "estateAgentSggNm": null,
        "dealYear": "2023",
        "dealMonth": "5",
        "dealDay": "22"
      },
      {
        "sggCd": "11215",
        "sggNm": "광진구",
        "umdNm": "자양동",
        "jimok": "도로",
        "jibun": "8*",
        "dealAmount": "855",
        "dealArea": "1.35",
        "dealingGbn": "직거래",
        "landUse": "제2종일반주거지역",
        "shareDealingType": "지분",
        "cdealType": null,
        "cdealDay": null,
        "estateAgentSggNm": null,
        "dealYear": "2023",
        "dealMonth": "5",
        "dealDay": "22"
      },
      {
        "sggCd": "11215",
        "sggNm": "광진구",
        "umdNm": "자양동",
        "jimok": "도로",
        "jibun": "8*",
        "dealAmount": "973",
        "dealArea": "1.54",
        "dealingGbn": "직거래",
        "landUse": "제2종일반주거지역",
        "shareDealingType": "지분",
        "cdealType": null,
        "cdealDay": null,
        "estateAgentSggNm": null,
        "dealYear": "2023",
        "dealMonth": "5",
        "dealDay": "22"
      },
      {
        "sggCd": "11215",
        "sggNm": "광진구",
        "umdNm": "자양동",
        "jimok": "도로",
        "jibun": "8*",
        "dealAmount": "953",
        "dealArea": "1.5",
        "dealingGbn": "직거래",
        "landUse": "제2종일반주거지역",
        "shareDealingType": "지분",
        "cdealType": null,
        "cdealDay": null,
        "estateAgentSggNm": null,
        "dealYear": "2023",
        "dealMonth": "5",
        "dealDay": "22"
      },
      {
        "sggCd": "11215",
        "sggNm": "광진구",
        "umdNm": "자양동",
        "jimok": "도로",
        "jibun": "8*",
        "dealAmount": "979",
        "dealArea": "1.54",
        "dealingGbn": "직거래",
        "landUse": "제2종일반주거지역",
        "shareDealingType": "지분",
        "cdealType": null,
        "cdealDay": null,
        "estateAgentSggNm": null,
        "dealYear": "2023",
        "dealMonth": "5",
        "dealDay": "22"
      },
      {
        "sggCd": "11215",
        "sggNm": "광진구",
        "umdNm": "자양동",
        "jimok": "도로",
        "jibun": "8*",
        "dealAmount": "953",
        "dealArea": "1.5",
        "dealingGbn": "직거래",
        "landUse": "제2종일반주거지역",
        "shareDealingType": "지분",
        "cdealType": null,
        "cdealDay": null,
        "estateAgentSggNm": null,
        "dealYear": "2023",
        "dealMonth": "5",
        "dealDay": "22"
      },
      {
        "sggCd": "11215",
        "sggNm": "광진구",
        "umdNm": "자양동",
        "jimok": "도로",
        "jibun": "8*",
        "dealAmount": "953",
        "dealArea": "1.5",
        "dealingGbn": "직거래",
        "landUse": "제2종일반주거지역",
        "shareDealingType": "지분",
        "cdealType": null,
        "cdealDay": null,
        "estateAgentSggNm": null,
        "dealYear": "2023",
        "dealMonth": "5",
        "dealDay": "22"
      },
      {
        "sggCd": "11215",
        "sggNm": "광진구",
        "umdNm": "자양동",
        "jimok": "도로",
        "jibun": "8*",
        "dealAmount": "994",
        "dealArea": "1.57",
        "dealingGbn": "직거래",
        "landUse": "제2종일반주거지역",
        "shareDealingType": "지분",
        "cdealType": null,
        "cdealDay": null,
        "estateAgentSggNm": null,
        "dealYear": "2023",
        "dealMonth": "5",
        "dealDay": "22"
      },
      {
        "sggCd": "11215",
        "sggNm": "광진구",
        "umdNm": "자양동",
        "jimok": "도로",
        "jibun": "8*",
        "dealAmount": "850",
        "dealArea": "1.34",
        "dealingGbn": "직거래",
        "landUse": "제2종일반주거지역",
        "shareDealingType": "지분",
        "cdealType": null,
        "cdealDay": null,
        "estateAgentSggNm": null,
        "dealYear": "2023",
        "dealMonth": "5",
        "dealDay": "22"
      },
      {
        "sggCd": "11215",
        "sggNm": "광진구",
        "umdNm": "자양동",
        "jimok": "도로",
        "jibun": "8*",
        "dealAmount": "958",
        "dealArea": "1.51",
        "dealingGbn": "직거래",
        "landUse": "제2종일반주거지역",
        "shareDealingType": "지분",
        "cdealType": null,
        "cdealDay": null,
        "estateAgentSggNm": null,
        "dealYear": "2023",
        "dealMonth": "5",
        "dealDay": "22"
      },
      {
        "sggCd": "11215",
        "sggNm": "광진구",
        "umdNm": "자양동",
        "jimok": "도로",
        "jibun": "8*",
        "dealAmount": "953",
        "dealArea": "1.5",
        "dealingGbn": "직거래",
        "landUse": "제2종일반주거지역",
        "shareDealingType": "지분",
        "cdealType": null,
        "cdealDay": null,
        "estateAgentSggNm": null,
        "dealYear": "2023",
        "dealMonth": "5",
        "dealDay": "22"
      },
      {
        "sggCd": "11215",
        "sggNm": "광진구",
        "umdNm": "자양동",
        "jimok": "도로",
        "jibun": "8*",
        "dealAmount": "973",
        "dealArea": "1.54",
        "dealingGbn": "직거래",
        "landUse": "제2종일반주거지역",
        "shareDealingType": "지분",
        "cdealType": null,
        "cdealDay": null,
        "estateAgentSggNm": null,
        "dealYear": "2023",
        "dealMonth": "5",
        "dealDay": "22"
      },
      {
        "sggCd": "11215",
        "sggNm": "광진구",
        "umdNm": "자양동",
        "jimok": "도로",
        "jibun": "8*",
        "dealAmount": "973",
        "dealArea": "1.54",
        "dealingGbn": "직거래",
        "landUse": "제2종일반주거지역",
        "shareDealingType": "지분",
        "cdealType": null,
        "cdealDay": null,
        "estateAgentSggNm": null,
        "dealYear": "2023",
        "dealMonth": "5",
        "dealDay": "22"
      },
      {
        "sggCd": "11215",
        "sggNm": "광진구",
        "umdNm": "자양동",
        "jimok": "도로",
        "jibun": "8*",
        "dealAmount": "1,269",
        "dealArea": "2",
        "dealingGbn": "직거래",
        "landUse": "제2종일반주거지역",
        "shareDealingType": "지분",
        "cdealType": null,
        "cdealDay": null,
        "estateAgentSggNm": null,
        "dealYear": "2023",
        "dealMonth": "5",
        "dealDay": "22"
      },
      {
        "sggCd": "11215",
        "sggNm": "광진구",
        "umdNm": "자양동",
        "jimok": "도로",
        "jibun": "8*",
        "dealAmount": "958",
        "dealArea": "1.51",
        "dealingGbn": "직거래",
        "landUse": "제2종일반주거지역",
        "shareDealingType": "지분",
        "cdealType": null,
        "cdealDay": null,
        "estateAgentSggNm": null,
        "dealYear": "2023",
        "dealMonth": "5",
        "dealDay": "22"
      },
      {
        "sggCd": "11215",
        "sggNm": "광진구",
        "umdNm": "자양동",
        "jimok": "도로",
        "jibun": "8*",
        "dealAmount": "994",
        "dealArea": "1.57",
        "dealingGbn": "직거래",
        "landUse": "제2종일반주거지역",
        "shareDealingType": "지분",
        "cdealType": null,
        "cdealDay": null,
        "estateAgentSggNm": null,
        "dealYear": "2023",
        "dealMonth": "5",
        "dealDay": "22"
      },
      {
        "sggCd": "11215",
        "sggNm": "광진구",
        "umdNm": "자양동",
        "jimok": "도로",
        "jibun": "8*",
        "dealAmount": "956",
        "dealArea": "1.51",
        "dealingGbn": "직거래",
        "landUse": "제2종일반주거지역",
        "shareDealingType": "지분",
        "cdealType": null,
        "cdealDay": null,
        "estateAgentSggNm": null,
        "dealYear": "2023",
        "dealMonth": "5",
        "dealDay": "22"
      },
      {
        "sggCd": "11215",
        "sggNm": "광진구",
        "umdNm": "자양동",
        "jimok": "도로",
        "jibun": "8*",
        "dealAmount": "958",
        "dealArea": "1.51",
        "dealingGbn": "직거래",
        "landUse": "제2종일반주거지역",
        "shareDealingType": "지분",
        "cdealType": null,
        "cdealDay": null,
        "estateAgentSggNm": null,
        "dealYear": "2023",
        "dealMonth": "5",
        "dealDay": "22"
      },
      {
        "sggCd": "11215",
        "sggNm": "광진구",
        "umdNm": "자양동",
        "jimok": "도로",
        "jibun": "8*",
        "dealAmount": "973",
        "dealArea": "1.54",
        "dealingGbn": "직거래",
        "landUse": "제2종일반주거지역",
        "shareDealingType": "지분",
        "cdealType": null,
        "cdealDay": null,
        "estateAgentSggNm": null,
        "dealYear": "2023",
        "dealMonth": "5",
        "dealDay": "22"
      },
      {
        "sggCd": "11215",
        "sggNm": "광진구",
        "umdNm": "자양동",
        "jimok": "도로",
        "jibun": "8*",
        "dealAmount": "994",
        "dealArea": "1.57",
        "dealingGbn": "직거래",
        "landUse": "제2종일반주거지역",
        "shareDealingType": "지분",
        "cdealType": null,
        "cdealDay": null,
        "estateAgentSggNm": null,
        "dealYear": "2023",
        "dealMonth": "5",
        "dealDay": "22"
      },
      {
        "sggCd": "11215",
        "sggNm": "광진구",
        "umdNm": "자양동",
        "jimok": "도로",
        "jibun": "8*",
        "dealAmount": "953",
        "dealArea": "1.5",
        "dealingGbn": "직거래",
        "landUse": "제2종일반주거지역",
        "shareDealingType": "지분",
        "cdealType": null,
        "cdealDay": null,
        "estateAgentSggNm": null,
        "dealYear": "2023",
        "dealMonth": "5",
        "dealDay": "22"
      },
      {
        "sggCd": "11215",
        "sggNm": "광진구",
        "umdNm": "자양동",
        "jimok": "도로",
        "jibun": "8*",
        "dealAmount": "1,241",
        "dealArea": "1.96",
        "dealingGbn": "직거래",
        "landUse": "제2종일반주거지역",
        "shareDealingType": "지분",
        "cdealType": null,
        "cdealDay": null,
        "estateAgentSggNm": null,
        "dealYear": "2023",
        "dealMonth": "5",
        "dealDay": "22"
      },
      {
        "sggCd": "11215",
        "sggNm": "광진구",
        "umdNm": "자양동",
        "jimok": "도로",
        "jibun": "8*",
        "dealAmount": "792",
        "dealArea": "1.25",
        "dealingGbn": "직거래",
        "landUse": "제2종일반주거지역",
        "shareDealingType": "지분",
        "cdealType": null,
        "cdealDay": null,
        "estateAgentSggNm": null,
        "dealYear": "2023",
        "dealMonth": "5",
        "dealDay": "22"
      },
      {
        "sggCd": "11215",
        "sggNm": "광진구",
        "umdNm": "자양동",
        "jimok": "도로",
        "jibun": "8*",
        "dealAmount": "1,270",
        "dealArea": "2",
        "dealingGbn": "직거래",
        "landUse": "제2종일반주거지역",
        "shareDealingType": "지분",
        "cdealType": null,
        "cdealDay": null,
        "estateAgentSggNm": null,
        "dealYear": "2023",
        "dealMonth": "5",
        "dealDay": "22"
      },
      {
        "sggCd": "11215",
        "sggNm": "광진구",
        "umdNm": "자양동",
        "jimok": "도로",
        "jibun": "8*",
        "dealAmount": "970",
        "dealArea": "1.53",
        "dealingGbn": "직거래",
        "landUse": "제2종일반주거지역",
        "shareDealingType": "지분",
        "cdealType": null,
        "cdealDay": null,
        "estateAgentSggNm": null,
        "dealYear": "2023",
        "dealMonth": "5",
        "dealDay": "22"
      },
      {
        "sggCd": "11215",
        "sggNm": "광진구",
        "umdNm": "자양동",
        "jimok": "도로",
        "jibun": "8*",
        "dealAmount": "958",
        "dealArea": "1.51",
        "dealingGbn": "직거래",
        "landUse": "제2종일반주거지역",
        "shareDealingType": "지분",
        "cdealType": null,
        "cdealDay": null,
        "estateAgentSggNm": null,
        "dealYear": "2023",
        "dealMonth": "5",
        "dealDay": "22"
      },
      {
        "sggCd": "11215",
        "sggNm": "광진구",
        "umdNm": "자양동",
        "jimok": "도로",
        "jibun": "8*",
        "dealAmount": "953",
        "dealArea": "1.5",
        "dealingGbn": "직거래",
        "landUse": "제2종일반주거지역",
        "shareDealingType": "지분",
        "cdealType": null,
        "cdealDay": null,
        "estateAgentSggNm": null,
        "dealYear": "2023",
        "dealMonth": "5",
        "dealDay": "22"
      },
      {
        "sggCd": "11215",
        "sggNm": "광진구",
        "umdNm": "자양동",
        "jimok": "도로",
        "jibun": "8*",
        "dealAmount": "994",
        "dealArea": "1.57",
        "dealingGbn": "직거래",
        "landUse": "제2종일반주거지역",
        "shareDealingType": "지분",
        "cdealType": null,
        "cdealDay": null,
        "estateAgentSggNm": null,
        "dealYear": "2023",
        "dealMonth": "5",
        "dealDay": "22"
      },
      {
        "sggCd": "11215",
        "sggNm": "광진구",
        "umdNm": "자양동",
        "jimok": "도로",
        "jibun": "8*",
        "dealAmount": "973",
        "dealArea": "1.54",
        "dealingGbn": "직거래",
        "landUse": "제2종일반주거지역",
        "shareDealingType": "지분",
        "cdealType": null,
        "cdealDay": null,
        "estateAgentSggNm": null,
        "dealYear": "2023",
        "dealMonth": "5",
        "dealDay": "22"
      },
      {
        "sggCd": "11215",
        "sggNm": "광진구",
        "umdNm": "자양동",
        "jimok": "도로",
        "jibun": "8*",
        "dealAmount": "973",
        "dealArea": "1.54",
        "dealingGbn": "직거래",
        "landUse": "제2종일반주거지역",
        "shareDealingType": "지분",
        "cdealType": null,
        "cdealDay": null,
        "estateAgentSggNm": null,
        "dealYear": "2023",
        "dealMonth": "5",
        "dealDay": "22"
      },
      {
        "sggCd": "11215",
        "sggNm": "광진구",
        "umdNm": "자양동",
        "jimok": "도로",
        "jibun": "8*",
        "dealAmount": "1,227",
        "dealArea": "1.94",
        "dealingGbn": "직거래",
        "landUse": "제2종일반주거지역",
        "shareDealingType": "지분",
        "cdealType": null,
        "cdealDay": null,
        "estateAgentSggNm": null,
        "dealYear": "2023",
        "dealMonth": "5",
        "dealDay": "22"
      },
      {
        "sggCd": "11215",
        "sggNm": "광진구",
        "umdNm": "자양동",
        "jimok": "도로",
        "jibun": "8*",
        "dealAmount": "1,241",
        "dealArea": "1.96",
        "dealingGbn": "직거래",
        "landUse": "제2종일반주거지역",
        "shareDealingType": "지분",
        "cdealType": null,
        "cdealDay": null,
        "estateAgentSggNm": null,
        "dealYear": "2023",
        "dealMonth": "5",
        "dealDay": "22"
      },
      {
        "sggCd": "11215",
        "sggNm": "광진구",
        "umdNm": "자양동",
        "jimok": "도로",
        "jibun": "8*",
        "dealAmount": "953",
        "dealArea": "1.5",
        "dealingGbn": "직거래",
        "landUse": "제2종일반주거지역",
        "shareDealingType": "지분",
        "cdealType": null,
        "cdealDay": null,
        "estateAgentSggNm": null,
        "dealYear": "2023",
        "dealMonth": "5",
        "dealDay": "22"
      },
      {
        "sggCd": "11215",
        "sggNm": "광진구",
        "umdNm": "자양동",
        "jimok": "도로",
        "jibun": "8*",
        "dealAmount": "953",
        "dealArea": "1.5",
        "dealingGbn": "직거래",
        "landUse": "제2종일반주거지역",
        "shareDealingType": "지분",
        "cdealType": null,
        "cdealDay": null,
        "estateAgentSggNm": null,
        "dealYear": "2023",
        "dealMonth": "5",
        "dealDay": "22"
      },
      {
        "sggCd": "11215",
        "sggNm": "광진구",
        "umdNm": "자양동",
        "jimok": "도로",
        "jibun": "8*",
        "dealAmount": "979",
        "dealArea": "1.54",
        "dealingGbn": "직거래",
        "landUse": "제2종일반주거지역",
        "shareDealingType": "지분",
        "cdealType": null,
        "cdealDay": null,
        "estateAgentSggNm": null,
        "dealYear": "2023",
        "dealMonth": "5",
        "dealDay": "22"
      },
      {
        "sggCd": "11215",
        "sggNm": "광진구",
        "umdNm": "자양동",
        "jimok": "도로",
        "jibun": "8*",
        "dealAmount": "855",
        "dealArea": "1.35",
        "dealingGbn": "직거래",
        "landUse": "제2종일반주거지역",
        "shareDealingType": "지분",
        "cdealType": null,
        "cdealDay": null,
        "estateAgentSggNm": null,
        "dealYear": "2023",
        "dealMonth": "5",
        "dealDay": "22"
      },
      {
        "sggCd": "11215",
        "sggNm": "광진구",
        "umdNm": "자양동",
        "jimok": "도로",
        "jibun": "8*",
        "dealAmount": "952",
        "dealArea": "1.5",
        "dealingGbn": "직거래",
        "landUse": "제2종일반주거지역",
        "shareDealingType": "지분",
        "cdealType": null,
        "cdealDay": null,
        "estateAgentSggNm": null,
        "dealYear": "2023",
        "dealMonth": "5",
        "dealDay": "22"
      },
      {
        "sggCd": "11215",
        "sggNm": "광진구",
        "umdNm": "자양동",
        "jimok": "도로",
        "jibun": "8*",
        "dealAmount": "953",
        "dealArea": "1.5",
        "dealingGbn": "직거래",
        "landUse": "제2종일반주거지역",
        "shareDealingType": "지분",
        "cdealType": null,
        "cdealDay": null,
        "estateAgentSggNm": null,
        "dealYear": "2023",
        "dealMonth": "5",
        "dealDay": "22"
      },
      {
        "sggCd": "11215",
        "sggNm": "광진구",
        "umdNm": "자양동",
        "jimok": "도로",
        "jibun": "8*",
        "dealAmount": "788",
        "dealArea": "1.24",
        "dealingGbn": "직거래",
        "landUse": "제2종일반주거지역",
        "shareDealingType": "지분",
        "cdealType": null,
        "cdealDay": null,
        "estateAgentSggNm": null,
        "dealYear": "2023",
        "dealMonth": "5",
        "dealDay": "22"
      },
      {
        "sggCd": "11215",
        "sggNm": "광진구",
        "umdNm": "자양동",
        "jimok": "도로",
        "jibun": "8*",
        "dealAmount": "1,270",
        "dealArea": "2",
        "dealingGbn": "직거래",
        "landUse": "제2종일반주거지역",
        "shareDealingType": "지분",
        "cdealType": null,
        "cdealDay": null,
        "estateAgentSggNm": null,
        "dealYear": "2023",
        "dealMonth": "5",
        "dealDay": "22"
      },
      {
        "sggCd": "11215",
        "sggNm": "광진구",
        "umdNm": "자양동",
        "jimok": "도로",
        "jibun": "8*",
        "dealAmount": "994",
        "dealArea": "1.57",
        "dealingGbn": "직거래",
        "landUse": "제2종일반주거지역",
        "shareDealingType": "지분",
        "cdealType": null,
        "cdealDay": null,
        "estateAgentSggNm": null,
        "dealYear": "2023",
        "dealMonth": "5",
        "dealDay": "22"
      },
      {
        "sggCd": "11215",
        "sggNm": "광진구",
        "umdNm": "자양동",
        "jimok": "도로",
        "jibun": "8*",
        "dealAmount": "1,299",
        "dealArea": "2.05",
        "dealingGbn": "직거래",
        "landUse": "제2종일반주거지역",
        "shareDealingType": "지분",
        "cdealType": null,
        "cdealDay": null,
        "estateAgentSggNm": null,
        "dealYear": "2023",
        "dealMonth": "5",
        "dealDay": "22"
      },
      {
        "sggCd": "11215",
        "sggNm": "광진구",
        "umdNm": "자양동",
        "jimok": "도로",
        "jibun": "8*",
        "dealAmount": "1,270",
        "dealArea": "2",
        "dealingGbn": "직거래",
        "landUse": "제2종일반주거지역",
        "shareDealingType": "지분",
        "cdealType": null,
        "cdealDay": null,
        "estateAgentSggNm": null,
        "dealYear": "2023",
        "dealMonth": "5",
        "dealDay": "22"
      },
      {
        "sggCd": "11215",
        "sggNm": "광진구",
        "umdNm": "자양동",
        "jimok": "도로",
        "jibun": "8*",
        "dealAmount": "994",
        "dealArea": "1.57",
        "dealingGbn": "직거래",
        "landUse": "제2종일반주거지역",
        "shareDealingType": "지분",
        "cdealType": null,
        "cdealDay": null,
        "estateAgentSggNm": null,
        "dealYear": "2023",
        "dealMonth": "5",
        "dealDay": "22"
      },
      {
        "sggCd": "11215",
        "sggNm": "광진구",
        "umdNm": "자양동",
        "jimok": "도로",
        "jibun": "8*",
        "dealAmount": "973",
        "dealArea": "1.54",
        "dealingGbn": "직거래",
        "landUse": "제2종일반주거지역",
        "shareDealingType": "지분",
        "cdealType": null,
        "cdealDay": null,
        "estateAgentSggNm": null,
        "dealYear": "2023",
        "dealMonth": "5",
        "dealDay": "22"
      },
      {
        "sggCd": "11215",
        "sggNm": "광진구",
        "umdNm": "자양동",
        "jimok": "도로",
        "jibun": "8*",
        "dealAmount": "953",
        "dealArea": "1.5",
        "dealingGbn": "직거래",
        "landUse": "제2종일반주거지역",
        "shareDealingType": "지분",
        "cdealType": null,
        "cdealDay": null,
        "estateAgentSggNm": null,
        "dealYear": "2023",
        "dealMonth": "5",
        "dealDay": "22"
      },
      {
        "sggCd": "11215",
        "sggNm": "광진구",
        "umdNm": "자양동",
        "jimok": "도로",
        "jibun": "8*",
        "dealAmount": "953",
        "dealArea": "1.5",
        "dealingGbn": "직거래",
        "landUse": "제2종일반주거지역",
        "shareDealingType": "지분",
        "cdealType": null,
        "cdealDay": null,
        "estateAgentSggNm": null,
        "dealYear": "2023",
        "dealMonth": "5",
        "dealDay": "22"
      },
      {
        "sggCd": "11215",
        "sggNm": "광진구",
        "umdNm": "자양동",
        "jimok": "도로",
        "jibun": "8*",
        "dealAmount": "942",
        "dealArea": "1.49",
        "dealingGbn": "직거래",
        "landUse": "제2종일반주거지역",
        "shareDealingType": "지분",
        "cdealType": null,
        "cdealDay": null,
        "estateAgentSggNm": null,
        "dealYear": "2023",
        "dealMonth": "5",
        "dealDay": "22"
      },
      {
        "sggCd": "11215",
        "sggNm": "광진구",
        "umdNm": "자양동",
        "jimok": "도로",
        "jibun": "8*",
        "dealAmount": "1,241",
        "dealArea": "1.96",
        "dealingGbn": "직거래",
        "landUse": "제2종일반주거지역",
        "shareDealingType": "지분",
        "cdealType": null,
        "cdealDay": null,
        "estateAgentSggNm": null,
        "dealYear": "2023",
        "dealMonth": "5",
        "dealDay": "22"
      },
      {
        "sggCd": "11215",
        "sggNm": "광진구",
        "umdNm": "자양동",
        "jimok": "도로",
        "jibun": "8*",
        "dealAmount": "956",
        "dealArea": "1.51",
        "dealingGbn": "직거래",
        "landUse": "제2종일반주거지역",
        "shareDealingType": "지분",
        "cdealType": null,
        "cdealDay": null,
        "estateAgentSggNm": null,
        "dealYear": "2023",
        "dealMonth": "5",
        "dealDay": "22"
      },
      {
        "sggCd": "11215",
        "sggNm": "광진구",
        "umdNm": "자양동",
        "jimok": "도로",
        "jibun": "8*",
        "dealAmount": "953",
        "dealArea": "1.5",
        "dealingGbn": "직거래",
        "landUse": "제2종일반주거지역",
        "shareDealingType": "지분",
        "cdealType": null,
        "cdealDay": null,
        "estateAgentSggNm": null,
        "dealYear": "2023",
        "dealMonth": "5",
        "dealDay": "22"
      },
      {
        "sggCd": "11215",
        "sggNm": "광진구",
        "umdNm": "자양동",
        "jimok": "도로",
        "jibun": "8*",
        "dealAmount": "988",
        "dealArea": "1.56",
        "dealingGbn": "직거래",
        "landUse": "제2종일반주거지역",
        "shareDealingType": "지분",
        "cdealType": null,
        "cdealDay": null,
        "estateAgentSggNm": null,
        "dealYear": "2023",
        "dealMonth": "5",
        "dealDay": "22"
      },
      {
        "sggCd": "11215",
        "sggNm": "광진구",
        "umdNm": "자양동",
        "jimok": "도로",
        "jibun": "8*",
        "dealAmount": "953",
        "dealArea": "1.5",
        "dealingGbn": "직거래",
        "landUse": "제2종일반주거지역",
        "shareDealingType": "지분",
        "cdealType": null,
        "cdealDay": null,
        "estateAgentSggNm": null,
        "dealYear": "2023",
        "dealMonth": "5",
        "dealDay": "22"
      },
      {
        "sggCd": "11215",
        "sggNm": "광진구",
        "umdNm": "자양동",
        "jimok": "도로",
        "jibun": "8*",
        "dealAmount": "973",
        "dealArea": "1.54",
        "dealingGbn": "직거래",
        "landUse": "제2종일반주거지역",
        "shareDealingType": "지분",
        "cdealType": null,
        "cdealDay": null,
        "estateAgentSggNm": null,
        "dealYear": "2023",
        "dealMonth": "5",
        "dealDay": "22"
      },
      {
        "sggCd": "11215",
        "sggNm": "광진구",
        "umdNm": "자양동",
        "jimok": "도로",
        "jibun": "8*",
        "dealAmount": "973",
        "dealArea": "1.54",
        "dealingGbn": "직거래",
        "landUse": "제2종일반주거지역",
        "shareDealingType": "지분",
        "cdealType": null,
        "cdealDay": null,
        "estateAgentSggNm": null,
        "dealYear": "2023",
        "dealMonth": "5",
        "dealDay": "22"
      },
      {
        "sggCd": "11215",
        "sggNm": "광진구",
        "umdNm": "자양동",
        "jimok": "대",
        "jibun": "6**",
        "dealAmount": "13,000",
        "dealArea": "37.58",
        "dealingGbn": "직거래",
        "landUse": "제3종일반주거지역",
        "shareDealingType": "지분",
        "cdealType": null,
        "cdealDay": null,
        "estateAgentSggNm": null,
        "dealYear": "2023",
        "dealMonth": "5",
        "dealDay": "30"
      },
      {
        "sggCd": "11215",
        "sggNm": "광진구",
        "umdNm": "자양동",
        "jimok": "대",
        "jibun": "6**",
        "dealAmount": "13,000",
        "dealArea": "1.06",
        "dealingGbn": "직거래",
        "landUse": "제3종일반주거지역",
        "shareDealingType": "지분",
        "cdealType": null,
        "cdealDay": null,
        "estateAgentSggNm": null,
        "dealYear": "2023",
        "dealMonth": "5",
        "dealDay": "30"
      },
      {
        "sggCd": "11215",
        "sggNm": "광진구",
        "umdNm": "구의동",
        "jimok": "도로",
        "jibun": "2**",
        "dealAmount": "1,500",
        "dealArea": "3.31",
        "dealingGbn": "직거래",
        "landUse": "제2종일반주거지역",
        "shareDealingType": "지분",
        "cdealType": null,
        "cdealDay": null,
        "estateAgentSggNm": null,
        "dealYear": "2023",
        "dealMonth": "5",
        "dealDay": "1"
      },
      {
        "sggCd": "11215",
        "sggNm": "광진구",
        "umdNm": "구의동",
        "jimok": "도로",
        "jibun": "2**",
        "dealAmount": "3,000",
        "dealArea": "6.61",
        "dealingGbn": "직거래",
        "landUse": "제2종일반주거지역",
        "shareDealingType": "지분",
        "cdealType": null,
        "cdealDay": null,
        "estateAgentSggNm": null,
        "dealYear": "2023",
        "dealMonth": "5",
        "dealDay": "1"
      }
    ]
  },
  {
    "lawd_cd": "11215",
    "deal_ymd": "202306",
    "total_count": 1,
    "items": [
      {
        "sggCd": "11215",
        "sggNm": "광진구",
        "umdNm": "자양동",
        "jimok": "대",
        "jibun": "6**",
        "dealAmount": "1,612",
        "dealArea": "1.3",
        "dealingGbn": "직거래",
        "landUse": "제2종일반주거지역",
        "shareDealingType": null,
        "cdealType": null,
        "cdealDay": null,
        "estateAgentSggNm": null,
        "dealYear": "2023",
        "dealMonth": "6",
        "dealDay": "19"
      }
    ]
  },
  {
    "lawd_cd": "11215",
    "deal_ymd": "202307",
    "total_count": 2,
    "items": [
      {
        "sggCd": "11215",
        "sggNm": "광진구",
        "umdNm": "화양동",
        "jimok": "대",
        "jibun": "4**",
        "dealAmount": "12,100",
        "dealArea": "18",
        "dealingGbn": "직거래",
        "landUse": "제3종일반주거지역",
        "shareDealingType": null,
        "cdealType": null,
        "cdealDay": null,
        "estateAgentSggNm": null,
        "dealYear": "2023",
        "dealMonth": "7",
        "dealDay": "5"
      },
      {
        "sggCd": "11215",
        "sggNm": "광진구",
        "umdNm": "화양동",
        "jimok": "임야",
        "jibun": "9*",
        "dealAmount": "16,000",
        "dealArea": "13",
        "dealingGbn": "직거래",
        "landUse": "준주거지역",
        "shareDealingType": null,
        "cdealType": null,
        "cdealDay": null,
        "estateAgentSggNm": null,
        "dealYear": "2023",
        "dealMonth": "7",
        "dealDay": "19"
      }
    ]
  },
  {
    "lawd_cd": "11215",
    "deal_ymd": "202308",
    "total_count": 14,
    "items": [
      {
        "sggCd": "11215",
        "sggNm": "광진구",
        "umdNm": "자양동",
        "jimok": "도로",
        "jibun": "5**",
        "dealAmount": "17,640",
        "dealArea": "58.34",
        "dealingGbn": "중개거래",
        "landUse": "제2종일반주거지역",
        "shareDealingType": "지분",
        "cdealType": null,
        "cdealDay": null,
        "estateAgentSggNm": "서울 광진구",
        "dealYear": "2023",
        "dealMonth": "8",
        "dealDay": "31"
      },
      {
        "sggCd": "11215",
        "sggNm": "광진구",
        "umdNm": "자양동",
        "jimok": "도로",
        "jibun": "5**",
        "dealAmount": "17,640",
        "dealArea": "58.33",
        "dealingGbn": "중개거래",
        "landUse": "제2종일반주거지역",
        "shareDealingType": "지분",
        "cdealType": null,
        "cdealDay": null,
        "estateAgentSggNm": "서울 광진구",
        "dealYear": "2023",
        "dealMonth": "8",
        "dealDay": "31"
      },
      {
        "sggCd": "11215",
        "sggNm": "광진구",
        "umdNm": "자양동",
        "jimok": "도로",
        "jibun": "5**",
        "dealAmount": "17,640",
        "dealArea": "58.33",
        "dealingGbn": "중개거래",
        "landUse": "제2종일반주거지역",
        "shareDealingType": "지분",
        "cdealType": null,
        "cdealDay": null,
        "estateAgentSggNm": "서울 광진구",
        "dealYear": "2023",
        "dealMonth": "8",
        "dealDay": "31"
      },
      {
        "sggCd": "11215",
        "sggNm": "광진구",
        "umdNm": "자양동",
        "jimok": "도로",
        "jibun": "5**",
        "dealAmount": "15,000",
        "dealArea": "49.6",
        "dealingGbn": "중개거래",
        "landUse": "제2종일반주거지역",
        "shareDealingType": "지분",
        "cdealType": null,
        "cdealDay": null,
        "estateAgentSggNm": "서울 광진구",
        "dealYear": "2023",
        "dealMonth": "8",
        "dealDay": "22"
      },
      {
        "sggCd": "11215",
        "sggNm": "광진구",
        "umdNm": "자양동",
        "jimok": "도로",
        "jibun": "5**",
        "dealAmount": "15,000",
        "dealArea": "49.6",
        "dealingGbn": "중개거래",
        "landUse": "제2종일반주거지역",
        "shareDealingType": "지분",
        "cdealType": null,
        "cdealDay": null,
        "estateAgentSggNm": "서울 광진구",
        "dealYear": "2023",
        "dealMonth": "8",
        "dealDay": "22"
      },
      {
        "sggCd": "11215",
        "sggNm": "광진구",
        "umdNm": "자양동",
        "jimok": "도로",
        "jibun": "5**",
        "dealAmount": "15,000",
        "dealArea": "49.6",
        "dealingGbn": "중개거래",
        "landUse": "제2종일반주거지역",
        "shareDealingType": "지분",
        "cdealType": null,
        "cdealDay": null,
        "estateAgentSggNm": "서울 광진구",
        "dealYear": "2023",
        "dealMonth": "8",
        "dealDay": "22"
      },
      {
        "sggCd": "11215",
        "sggNm": "광진구",
        "umdNm": "자양동",
        "jimok": "도로",
        "jibun": "5**",
        "dealAmount": "15,000",
        "dealArea": "49.6",
        "dealingGbn": "중개거래",
        "landUse": "제2종일반주거지역",
        "shareDealingType": "지분",
        "cdealType": null,
        "cdealDay": null,
        "estateAgentSggNm": "서울 광진구",
        "dealYear": "2023",
        "dealMonth": "8",
        "dealDay": "22"
      },
      {
        "sggCd": "11215",
        "sggNm": "광진구",
        "umdNm": "자양동",
        "jimok": "도로",
        "jibun": "5**",
        "dealAmount": "15,000",
        "dealArea": "49.6",
        "dealingGbn": "중개거래",
        "landUse": "제2종일반주거지역",
        "shareDealingType": "지분",
        "cdealType": null,
        "cdealDay": null,
        "estateAgentSggNm": "서울 광진구",
        "dealYear": "2023",
        "dealMonth": "8",
        "dealDay": "22"
      },
      {
        "sggCd": "11215",
        "sggNm": "광진구",
        "umdNm": "구의동",
        "jimok": "도로",
        "jibun": "2**",
        "dealAmount": "3,024",
        "dealArea": "21.37",
        "dealingGbn": "직거래",
        "landUse": "제2종일반주거지역",
        "shareDealingType": "지분",
        "cdealType": null,
        "cdealDay": null,
        "estateAgentSggNm": null,
        "dealYear": "2023",
        "dealMonth": "8",
        "dealDay": "16"
      },
      {
        "sggCd": "11215",
        "sggNm": "광진구",
        "umdNm": "구의동",
        "jimok": "도로",
        "jibun": "2**",
        "dealAmount": "9,576",
        "dealArea": "64.11",
        "dealingGbn": "직거래",
        "landUse": "제2종일반주거지역",
        "shareDealingType": "지분",
        "cdealType": null,
        "cdealDay": null,
        "estateAgentSggNm": null,
        "dealYear": "2023",
        "dealMonth": "8",
        "dealDay": "16"
      },
      {
        "sggCd": "11215",
        "sggNm": "광진구",
        "umdNm": "중곡동",
        "jimok": "도로",
        "jibun": "1**",
        "dealAmount": "5,850",
        "dealArea": "43",
        "dealingGbn": "직거래",
        "landUse": "제2종일반주거지역",
        "shareDealingType": "지분",
        "cdealType": null,
        "cdealDay": null,
        "estateAgentSggNm": null,
        "dealYear": "2023",
        "dealMonth": "8",
        "dealDay": "25"
      },
      {
        "sggCd": "11215",
        "sggNm": "광진구",
        "umdNm": "능동",
        "jimok": "도로",
        "jibun": "2**",
        "dealAmount": "12,500",
        "dealArea": "43.6",
        "dealingGbn": "직거래",
        "landUse": "제1종일반주거지역",
        "shareDealingType": null,
        "cdealType": null,
        "cdealDay": null,
        "estateAgentSggNm": null,
        "dealYear": "2023",
        "dealMonth": "8",
        "dealDay": "24"
      },
      {
        "sggCd": "11215",
        "sggNm": "광진구",
        "umdNm": "중곡동",
        "jimok": "도로",
        "jibun": "1**",
        "dealAmount": "4,500",
        "dealArea": "33",
        "dealingGbn": "직거래",
        "landUse": "제2종일반주거지역",
        "shareDealingType": "지분",
        "cdealType": null,
        "cdealDay": null,
        "estateAgentSggNm": null,
        "dealYear": "2023",
        "dealMonth": "8",
        "dealDay": "19"
      },
      {
        "sggCd": "11215",
        "sggNm": "광진구",
        "umdNm": "중곡동",
        "jimok": "도로",
        "jibun": "1**",
        "dealAmount": "4,500",
        "dealArea": "33",
        "dealingGbn": "직거래",
        "landUse": "제2종일반주거지역",
        "shareDealingType": "지분",
        "cdealType": null,
        "cdealDay": null,
        "estateAgentSggNm": null,
        "dealYear": "2023",
        "dealMonth": "8",
        "dealDay": "7"
      }
    ]
  },
  {
    "lawd_cd": "11215",
    "deal_ymd": "202309",
    "total_count": 5,
    "items": [
      {
        "sggCd": "11215",
        "sggNm": "광진구",
        "umdNm": "광장동",
        "jimok": "제방",
        "jibun": "1**",
        "dealAmount": "141,781",
        "dealArea": "233",
        "dealingGbn": "직거래",
        "landUse": "제3종일반주거지역",
        "shareDealingType": null,
        "cdealType": null,
        "cdealDay": null,
        "estateAgentSggNm": null,
        "dealYear": "2023",
        "dealMonth": "9",
        "dealDay": "21"
      },
      {
        "sggCd": "11215",
        "sggNm": "광진구",
        "umdNm": "광장동",
        "jimok": "도로",
        "jibun": "2**",
        "dealAmount": "26,712",
        "dealArea": "48",
        "dealingGbn": "직거래",
        "landUse": "제3종일반주거지역",
        "shareDealingType": null,
        "cdealType": null,
        "cdealDay": null,
        "estateAgentSggNm": null,
        "dealYear": "2023",
        "dealMonth": "9",
        "dealDay": "21"
      },
      {
        "sggCd": "11215",
        "sggNm": "광진구",
        "umdNm": "구의동",
        "jimok": "도로",
        "jibun": "2**",
        "dealAmount": "32,200",
        "dealArea": "85.47",
        "dealingGbn": "직거래",
        "landUse": "제2종일반주거지역",
        "shareDealingType": "지분",
        "cdealType": null,
        "cdealDay": null,
        "estateAgentSggNm": null,
        "dealYear": "2023",
        "dealMonth": "9",
        "dealDay": "20"
      },
      {
        "sggCd": "11215",
        "sggNm": "광진구",
        "umdNm": "구의동",
        "jimok": "도로",
        "jibun": "2**",
        "dealAmount": "2,000",
        "dealArea": "5.92",
        "dealingGbn": "직거래",
        "landUse": "제2종일반주거지역",
        "shareDealingType": "지분",
        "cdealType": null,
        "cdealDay": null,
        "estateAgentSggNm": null,
        "dealYear": "2023",
        "dealMonth": "9",
        "dealDay": "20"
      },
      {
        "sggCd": "11215",
        "sggNm": "광진구",
        "umdNm": "구의동",
        "jimok": "도로",
        "jibun": "2**",
        "dealAmount": "1,800",
        "dealArea": "4.36",
        "dealingGbn": "직거래",
        "landUse": "제2종일반주거지역",
        "shareDealingType": "지분",
        "cdealType": null,
        "cdealDay": null,
        "estateAgentSggNm": null,
        "dealYear": "2023",
        "dealMonth": "9",
        "dealDay": "20"
      }
    ]
  },
  {
    "lawd_cd": "11215",
    "deal_ymd": "202310",
    "total_count": 2,
    "items": [
      {
        "sggCd": "11215",
        "sggNm": "광진구",
        "umdNm": "자양동",
        "jimok": "도로",
        "jibun": "*",
        "dealAmount": "50,000",
        "dealArea": "35",
        "dealingGbn": "직거래",
        "landUse": "제2종일반주거지역",
        "shareDealingType": null,
        "cdealType": null,
        "cdealDay": null,
        "estateAgentSggNm": null,
        "dealYear": "2023",
        "dealMonth": "10",
        "dealDay": "26"
      },
      {
        "sggCd": "11215",
        "sggNm": "광진구",
        "umdNm": "광장동",
        "jimok": "대",
        "jibun": "2**",
        "dealAmount": "3,000",
        "dealArea": "4",
        "dealingGbn": "직거래",
        "landUse": "제2종일반주거지역",
        "shareDealingType": null,
        "cdealType": null,
        "cdealDay": null,
        "estateAgentSggNm": null,
        "dealYear": "2023",
        "dealMonth": "10",
        "dealDay": "12"
      }
    ]
  },
  {
    "lawd_cd": "11215",
    "deal_ymd": "202311",
    "total_count": 3,
    "items": [
      {
        "sggCd": "11215",
        "sggNm": "광진구",
        "umdNm": "구의동",
        "jimok": "도로",
        "jibun": "5**",
        "dealAmount": "372,623",
        "dealArea": "521.3",
        "dealingGbn": "직거래",
        "landUse": "제2종일반주거지역",
        "shareDealingType": null,
        "cdealType": null,
        "cdealDay": null,
        "estateAgentSggNm": null,
        "dealYear": "2023",
        "dealMonth": "11",
        "dealDay": "28"
      },
      {
        "sggCd": "11215",
        "sggNm": "광진구",
        "umdNm": "자양동",
        "jimok": "도로",
        "jibun": "8*",
        "dealAmount": "973",
        "dealArea": "1.54",
        "dealingGbn": "직거래",
        "landUse": "제2종일반주거지역",
        "shareDealingType": "지분",
        "cdealType": null,
        "cdealDay": null,
        "estateAgentSggNm": null,
        "dealYear": "2023",
        "dealMonth": "11",
        "dealDay": "16"
      },
      {
        "sggCd": "11215",
        "sggNm": "광진구",
        "umdNm": "자양동",
        "jimok": "도로",
        "jibun": "8*",
        "dealAmount": "994",
        "dealArea": "1.57",
        "dealingGbn": "직거래",
        "landUse": "제2종일반주거지역",
        "shareDealingType": "지분",
        "cdealType": null,
        "cdealDay": null,
        "estateAgentSggNm": null,
        "dealYear": "2023",
        "dealMonth": "11",
        "dealDay": "16"
      }
    ]
  },
  {
    "lawd_cd": "11215",
    "deal_ymd": "202312",
    "total_count": 4,
    "items": [
      {
        "sggCd": "11215",
        "sggNm": "광진구",
        "umdNm": "자양동",
        "jimok": "대",
        "jibun": "9*",
        "dealAmount": "260,000",
        "dealArea": "205",
        "dealingGbn": "중개거래",
        "landUse": "제2종일반주거지역",
        "shareDealingType": null,
        "cdealType": null,
        "cdealDay": null,
        "estateAgentSggNm": "서울 강남구, 서울 중구",
        "dealYear": "2023",
        "dealMonth": "12",
        "dealDay": "27"
      },
      {
        "sggCd": "11215",
        "sggNm": "광진구",
        "umdNm": "자양동",
        "jimok": "대",
        "jibun": "9*",
        "dealAmount": "230,000",
        "dealArea": "136",
        "dealingGbn": "중개거래",
        "landUse": "제2종일반주거지역",
        "shareDealingType": null,
        "cdealType": null,
        "cdealDay": null,
        "estateAgentSggNm": "서울 강남구, 서울 중구",
        "dealYear": "2023",
        "dealMonth": "12",
        "dealDay": "27"
      },
      {
        "sggCd": "11215",
        "sggNm": "광진구",
        "umdNm": "화양동",
        "jimok": "대",
        "jibun": "1**",
        "dealAmount": "238,000",
        "dealArea": "120.46",
        "dealingGbn": "직거래",
        "landUse": "준주거지역",
        "shareDealingType": "지분",
        "cdealType": null,
        "cdealDay": null,
        "estateAgentSggNm": null,
        "dealYear": "2023",
        "dealMonth": "12",
        "dealDay": "12"
      },
      {
        "sggCd": "11215",
        "sggNm": "광진구",
        "umdNm": "화양동",
        "jimok": "대",
        "jibun": "4**",
        "dealAmount": "42,000",
        "dealArea": "20.32",
        "dealingGbn": "직거래",
        "landUse": "준주거지역",
        "shareDealingType": "지분",
        "cdealType": null,
        "cdealDay": null,
        "estateAgentSggNm": null,
        "dealYear": "2023",
        "dealMonth": "12",
        "dealDay": "12"
      }
    ]
  },
  {
    "lawd_cd": "11215",
    "deal_ymd": "202201",
    "total_count": 20,
    "items": [
      {
        "sggCd": "11215",
        "sggNm": "광진구",
        "umdNm": "자양동",
        "jimok": "대",
        "jibun": "6**",
        "dealAmount": "88,000",
        "dealArea": "55.3",
        "dealingGbn": "중개거래",
        "landUse": "제3종일반주거지역",
        "shareDealingType": null,
        "cdealType": "O",
        "cdealDay": "22.06.23",
        "estateAgentSggNm": "서울 광진구",
        "dealYear": "2022",
        "dealMonth": "1",
        "dealDay": "28"
      },
      {
        "sggCd": "11215",
        "sggNm": "광진구",
        "umdNm": "자양동",
        "jimok": "대",
        "jibun": "6**",
        "dealAmount": "66,000",
        "dealArea": "40.8",
        "dealingGbn": "중개거래",
        "landUse": "제3종일반주거지역",
        "shareDealingType": null,
        "cdealType": "O",
        "cdealDay": "22.06.23",
        "estateAgentSggNm": "서울 광진구",
        "dealYear": "2022",
        "dealMonth": "1",
        "dealDay": "28"
      },
      {
        "sggCd": "11215",
        "sggNm": "광진구",
        "umdNm": "자양동",
        "jimok": "도로",
        "jibun": "5*",
        "dealAmount": "62,600",
        "dealArea": "132",
        "dealingGbn": "중개거래",
        "landUse": "제2종일반주거지역",
        "shareDealingType": "지분",
        "cdealType": null,
        "cdealDay": null,
        "estateAgentSggNm": "서울 성동구",
        "dealYear": "2022",
        "dealMonth": "1",
        "dealDay": "27"
      },
      {
        "sggCd": "11215",
        "sggNm": "광진구",
        "umdNm": "자양동",
        "jimok": "도로",
        "jibun": "5*",
        "dealAmount": "62,000",
        "dealArea": "99.17",
        "dealingGbn": "중개거래",
        "landUse": "제2종일반주거지역",
        "shareDealingType": "지분",
        "cdealType": null,
        "cdealDay": null,
        "estateAgentSggNm": "서울 성동구",
        "dealYear": "2022",
        "dealMonth": "1",
        "dealDay": "25"
      },
      {
        "sggCd": "11215",
        "sggNm": "광진구",
        "umdNm": "구의동",
        "jimok": "대",
        "jibun": "6**",
        "dealAmount": "136,500",
        "dealArea": "134",
        "dealingGbn": "중개거래",
        "landUse": "제1종일반주거지역",
        "shareDealingType": null,
        "cdealType": null,
        "cdealDay": null,
        "estateAgentSggNm": "서울 광진구 서울 서초구",
        "dealYear": "2022",
        "dealMonth": "1",
        "dealDay": "21"
      },
      {
        "sggCd": "11215",
        "sggNm": "광진구",
        "umdNm": "구의동",
        "jimok": "대",
        "jibun": "6**",
        "dealAmount": "27,300",
        "dealArea": "26",
        "dealingGbn": "중개거래",
        "landUse": "제1종일반주거지역",
        "shareDealingType": null,
        "cdealType": null,
        "cdealDay": null,
        "estateAgentSggNm": "서울 광진구 서울 서초구",
        "dealYear": "2022",
        "dealMonth": "1",
        "dealDay": "21"
      },
      {
        "sggCd": "11215",
        "sggNm": "광진구",
        "umdNm": "구의동",
        "jimok": "대",
        "jibun": "6**",
        "dealAmount": "31,200",
        "dealArea": "29",
        "dealingGbn": "중개거래",
        "landUse": "제1종일반주거지역",
        "shareDealingType": null,
        "cdealType": null,
        "cdealDay": null,
        "estateAgentSggNm": "서울 광진구 서울 서초구",
        "dealYear": "2022",
        "dealMonth": "1",
        "dealDay": "21"
      },
      {
        "sggCd": "11215",
        "sggNm": "광진구",
        "umdNm": "구의동",
        "jimok": "대",
        "jibun": "6**",
        "dealAmount": "75,000",
        "dealArea": "139",
        "dealingGbn": "중개거래",
        "landUse": "제1종일반주거지역",
        "shareDealingType": null,
        "cdealType": null,
        "cdealDay": null,
        "estateAgentSggNm": "서울 광진구 서울 서초구",
        "dealYear": "2022",
        "dealMonth": "1",
        "dealDay": "21"
      },
      {
        "sggCd": "11215",
        "sggNm": "광진구",
        "umdNm": "광장동",
        "jimok": "도로",
        "jibun": "2**",
        "dealAmount": "2,157",
        "dealArea": "14",
        "dealingGbn": "직거래",
        "landUse": "제2종일반주거지역",
        "shareDealingType": null,
        "cdealType": null,
        "cdealDay": null,
        "estateAgentSggNm": null,
        "dealYear": "2022",
        "dealMonth": "1",
        "dealDay": "28"
      },
      {
        "sggCd": "11215",
        "sggNm": "광진구",
        "umdNm": "자양동",
        "jimok": "도로",
        "jibun": "5*",
        "dealAmount": "50,000",
        "dealArea": "132",
        "dealingGbn": "중개거래",
        "landUse": "제2종일반주거지역",
        "shareDealingType": "지분",
        "cdealType": null,
        "cdealDay": null,
        "estateAgentSggNm": "서울 성동구",
        "dealYear": "2022",
        "dealMonth": "1",
        "dealDay": "24"
      },
      {
        "sggCd": "11215",
        "sggNm": "광진구",
        "umdNm": "자양동",
        "jimok": "도로",
        "jibun": "5*",
        "dealAmount": "50,000",
        "dealArea": "132",
        "dealingGbn": "중개거래",
        "landUse": "제2종일반주거지역",
        "shareDealingType": "지분",
        "cdealType": null,
        "cdealDay": null,
        "estateAgentSggNm": "서울 성동구",
        "dealYear": "2022",
        "dealMonth": "1",
        "dealDay": "24"
      },
      {
        "sggCd": "11215",
        "sggNm": "광진구",
        "umdNm": "자양동",
        "jimok": "도로",
        "jibun": "5*",
        "dealAmount": "50,000",
        "dealArea": "132",
        "dealingGbn": "중개거래",
        "landUse": "제2종일반주거지역",
        "shareDealingType": "지분",
        "cdealType": null,
        "cdealDay": null,
        "estateAgentSggNm": "서울 성동구",
        "dealYear": "2022",
        "dealMonth": "1",
        "dealDay": "21"
      },
      {
        "sggCd": "11215",
        "sggNm": "광진구",
        "umdNm": "중곡동",
        "jimok": "임야",
        "jibun": "1**",
        "dealAmount": "509",
        "dealArea": "33.05",
        "dealingGbn": "직거래",
        "landUse": "개발제한구역",
        "shareDealingType": "지분",
        "cdealType": null,
        "cdealDay": null,
        "estateAgentSggNm": null,
        "dealYear": "2022",
        "dealMonth": "1",
        "dealDay": "18"
      },
      {
        "sggCd": "11215",
        "sggNm": "광진구",
        "umdNm": "중곡동",
        "jimok": "임야",
        "jibun": "1**",
        "dealAmount": "1,018",
        "dealArea": "66.11",
        "dealingGbn": "직거래",
        "landUse": "개발제한구역",
        "shareDealingType": "지분",
        "cdealType": null,
        "cdealDay": null,
        "estateAgentSggNm": null,
        "dealYear": "2022",
        "dealMonth": "1",
        "dealDay": "18"
      },
      {
        "sggCd": "11215",
        "sggNm": "광진구",
        "umdNm": "자양동",
        "jimok": "도로",
        "jibun": "5*",
        "dealAmount": "50,000",
        "dealArea": "132",
        "dealingGbn": "중개거래",
        "landUse": "제2종일반주거지역",
        "shareDealingType": "지분",
        "cdealType": null,
        "cdealDay": null,
        "estateAgentSggNm": "서울 성동구",
        "dealYear": "2022",
        "dealMonth": "1",
        "dealDay": "20"
      },
      {
        "sggCd": "11215",
        "sggNm": "광진구",
        "umdNm": "자양동",
        "jimok": "도로",
        "jibun": "5*",
        "dealAmount": "50,000",
        "dealArea": "132",
        "dealingGbn": "중개거래",
        "landUse": "제2종일반주거지역",
        "shareDealingType": "지분",
        "cdealType": null,
        "cdealDay": null,
        "estateAgentSggNm": "서울 성동구",
        "dealYear": "2022",
        "dealMonth": "1",
        "dealDay": "21"
      },
      {
        "sggCd": "11215",
        "sggNm": "광진구",
        "umdNm": "자양동",
        "jimok": "도로",
        "jibun": "5*",
        "dealAmount": "51,000",
        "dealArea": "137",
        "dealingGbn": "중개거래",
        "landUse": "제2종일반주거지역",
        "shareDealingType": "지분",
        "cdealType": null,
        "cdealDay": null,
        "estateAgentSggNm": "서울 성동구",
        "dealYear": "2022",
        "dealMonth": "1",
        "dealDay": "22"
      },
      {
        "sggCd": "11215",
        "sggNm": "광진구",
        "umdNm": "자양동",
        "jimok": "도로",
        "jibun": "5*",
        "dealAmount": "50,000",
        "dealArea": "132",
        "dealingGbn": "중개거래",
        "landUse": "제2종일반주거지역",
        "shareDealingType": "지분",
        "cdealType": null,
        "cdealDay": null,
        "estateAgentSggNm": "서울 성동구",
        "dealYear": "2022",
        "dealMonth": "1",
        "dealDay": "19"
      },
      {
        "sggCd": "11215",
        "sggNm": "광진구",
        "umdNm": "자양동",
        "jimok": "도로",
        "jibun": "5*",
        "dealAmount": "70,000",
        "dealArea": "116",
        "dealingGbn": "중개거래",
        "landUse": "제2종일반주거지역",
        "shareDealingType": null,
        "cdealType": null,
        "cdealDay": null,
        "estateAgentSggNm": "서울 성동구",
        "dealYear": "2022",
        "dealMonth": "1",
        "dealDay": "4"
      },
      {
        "sggCd": "11215",
        "sggNm": "광진구",
        "umdNm": "자양동",
        "jimok": "도로",
        "jibun": "6**",
        "dealAmount": "70,100",
        "dealArea": "201.5",
        "dealingGbn": "직거래",
        "landUse": "제2종일반주거지역",
        "shareDealingType": "지분",
        "cdealType": null,
        "cdealDay": null,
        "estateAgentSggNm": null,
        "dealYear": "2022",
        "dealMonth": "1",
        "dealDay": "3"
      }
    ]
  },
  {
    "lawd_cd": "11215",
    "deal_ymd": "202202",
    "total_count": 6,
    "items": [
      {
        "sggCd": "11215",
        "sggNm": "광진구",
        "umdNm": "자양동",
        "jimok": "대",
        "jibun": "7*",
        "dealAmount": "2,750,000",
        "dealArea": "1012",
        "dealingGbn": "직거래",
        "landUse": "준주거지역",
        "shareDealingType": null,
        "cdealType": null,
        "cdealDay": null,
        "estateAgentSggNm": null,
        "dealYear": "2022",
        "dealMonth": "2",
        "dealDay": "8"
      },
      {
        "sggCd": "11215",
        "sggNm": "광진구",
        "umdNm": "자양동",
        "jimok": "대",
        "jibun": "6**",
        "dealAmount": "38,400",
        "dealArea": "29.05",
        "dealingGbn": "직거래",
        "landUse": "제2종일반주거지역",
        "shareDealingType": "지분",
        "cdealType": null,
        "cdealDay": null,
        "estateAgentSggNm": null,
        "dealYear": "2022",
        "dealMonth": "2",
        "dealDay": "28"
      },
      {
        "sggCd": "11215",
        "sggNm": "광진구",
        "umdNm": "자양동",
        "jimok": "대",
        "jibun": "6**",
        "dealAmount": "38,400",
        "dealArea": "29.05",
        "dealingGbn": "직거래",
        "landUse": "제2종일반주거지역",
        "shareDealingType": "지분",
        "cdealType": null,
        "cdealDay": null,
        "estateAgentSggNm": null,
        "dealYear": "2022",
        "dealMonth": "2",
        "dealDay": "28"
      },
      {
        "sggCd": "11215",
        "sggNm": "광진구",
        "umdNm": "자양동",
        "jimok": "대",
        "jibun": "6**",
        "dealAmount": "38,400",
        "dealArea": "29.05",
        "dealingGbn": "직거래",
        "landUse": "제2종일반주거지역",
        "shareDealingType": "지분",
        "cdealType": null,
        "cdealDay": null,
        "estateAgentSggNm": null,
        "dealYear": "2022",
        "dealMonth": "2",
        "dealDay": "28"
      },
      {
        "sggCd": "11215",
        "sggNm": "광진구",
        "umdNm": "자양동",
        "jimok": "대",
        "jibun": "6**",
        "dealAmount": "38,400",
        "dealArea": "29.05",
        "dealingGbn": "직거래",
        "landUse": "제2종일반주거지역",
        "shareDealingType": "지분",
        "cdealType": null,
        "cdealDay": null,
        "estateAgentSggNm": null,
        "dealYear": "2022",
        "dealMonth": "2",
        "dealDay": "28"
      },
      {
        "sggCd": "11215",
        "sggNm": "광진구",
        "umdNm": "광장동",
        "jimok": "임야",
        "jibun": "3**",
        "dealAmount": "10,000",
        "dealArea": "172",
        "dealingGbn": "직거래",
        "landUse": "자연녹지지역",
        "shareDealingType": "지분",
        "cdealType": null,
        "cdealDay": null,
        "estateAgentSggNm": null,
        "dealYear": "2022",
        "dealMonth": "2",
        "dealDay": "17"
      }
    ]
  },
  {
    "lawd_cd": "11215",
    "deal_ymd": "202203",
    "total_count": 7,
    "items": [
      {
        "sggCd": "11215",
        "sggNm": "광진구",
        "umdNm": "구의동",
        "jimok": "도로",
        "jibun": "2**",
        "dealAmount": "433",
        "dealArea": "2",
        "dealingGbn": "중개거래",
        "landUse": "제3종일반주거지역",
        "shareDealingType": null,
        "cdealType": null,
        "cdealDay": null,
        "estateAgentSggNm": "서울 강남구 서울 서초구",
        "dealYear": "2022",
        "dealMonth": "3",
        "dealDay": "30"
      },
      {
        "sggCd": "11215",
        "sggNm": "광진구",
        "umdNm": "구의동",
        "jimok": "도로",
        "jibun": "2**",
        "dealAmount": "433",
        "dealArea": "2",
        "dealingGbn": "중개거래",
        "landUse": "제3종일반주거지역",
        "shareDealingType": null,
        "cdealType": "O",
        "cdealDay": "23.09.19",
        "estateAgentSggNm": "서울 강남구, 서울 서초구",
        "dealYear": "2022",
        "dealMonth": "3",
        "dealDay": "30"
      },
      {
        "sggCd": "11215",
        "sggNm": "광진구",
        "umdNm": "중곡동",
        "jimok": "대",
        "jibun": "1**",
        "dealAmount": "3,800",
        "dealArea": "33",
        "dealingGbn": "직거래",
        "landUse": "제2종일반주거지역",
        "shareDealingType": "지분",
        "cdealType": null,
        "cdealDay": null,
        "estateAgentSggNm": null,
        "dealYear": "2022",
        "dealMonth": "3",
        "dealDay": "23"
      },
      {
        "sggCd": "11215",
        "sggNm": "광진구",
        "umdNm": "구의동",
        "jimok": "대",
        "jibun": "5*",
        "dealAmount": "78,300",
        "dealArea": "113.4",
        "dealingGbn": "직거래",
        "landUse": "제2종일반주거지역",
        "shareDealingType": null,
        "cdealType": null,
        "cdealDay": null,
        "estateAgentSggNm": null,
        "dealYear": "2022",
        "dealMonth": "3",
        "dealDay": "22"
      },
      {
        "sggCd": "11215",
        "sggNm": "광진구",
        "umdNm": "구의동",
        "jimok": "대",
        "jibun": "5*",
        "dealAmount": "99,700",
        "dealArea": "144.5",
        "dealingGbn": "직거래",
        "landUse": "제2종일반주거지역",
        "shareDealingType": null,
        "cdealType": null,
        "cdealDay": null,
        "estateAgentSggNm": null,
        "dealYear": "2022",
        "dealMonth": "3",
        "dealDay": "22"
      },
      {
        "sggCd": "11215",
        "sggNm": "광진구",
        "umdNm": "중곡동",
        "jimok": "도로",
        "jibun": "1**",
        "dealAmount": "1,679",
        "dealArea": "33",
        "dealingGbn": "직거래",
        "landUse": "제2종일반주거지역",
        "shareDealingType": "지분",
        "cdealType": null,
        "cdealDay": null,
        "estateAgentSggNm": null,
        "dealYear": "2022",
        "dealMonth": "3",
        "dealDay": "8"
      },
      {
        "sggCd": "11215",
        "sggNm": "광진구",
        "umdNm": "자양동",
        "jimok": "대",
        "jibun": "6**",
        "dealAmount": "180,000",
        "dealArea": "120.2",
        "dealingGbn": "직거래",
        "landUse": "제2종일반주거지역",
        "shareDealingType": null,
        "cdealType": null,
        "cdealDay": null,
        "estateAgentSggNm": null,
        "dealYear": "2022",
        "dealMonth": "3",
        "dealDay": "7"
      }
    ]
  },
  {
    "lawd_cd": "11215",
    "deal_ymd": "202204",
    "total_count": 3,
    "items": [
      {
        "sggCd": "11215",
        "sggNm": "광진구",
        "umdNm": "중곡동",
        "jimok": "임야",
        "jibun": "1**",
        "dealAmount": "1,231",
        "dealArea": "14",
        "dealingGbn": "직거래",
        "landUse": "제1종일반주거지역",
        "shareDealingType": null,
        "cdealType": null,
        "cdealDay": null,
        "estateAgentSggNm": null,
        "dealYear": "2022",
        "dealMonth": "4",
        "dealDay": "25"
      },
      {
        "sggCd": "11215",
        "sggNm": "광진구",
        "umdNm": "군자동",
        "jimok": "대",
        "jibun": "4**",
        "dealAmount": "360,000",
        "dealArea": "324.6",
        "dealingGbn": "중개거래",
        "landUse": "제3종일반주거지역",
        "shareDealingType": null,
        "cdealType": null,
        "cdealDay": null,
        "estateAgentSggNm": "서울 금천구",
        "dealYear": "2022",
        "dealMonth": "4",
        "dealDay": "22"
      },
      {
        "sggCd": "11215",
        "sggNm": "광진구",
        "umdNm": "자양동",
        "jimok": "대",
        "jibun": "2**",
        "dealAmount": "60,000",
        "dealArea": "78.6",
        "dealingGbn": "중개거래",
        "landUse": "제2종일반주거지역",
        "shareDealingType": null,
        "cdealType": null,
        "cdealDay": null,
        "estateAgentSggNm": "서울 광진구",
        "dealYear": "2022",
        "dealMonth": "4",
        "dealDay": "28"
      }
    ]
  },
  {
    "lawd_cd": "11215",
    "deal_ymd": "202205",
    "total_count": 7,
    "items": [
      {
        "sggCd": "11215",
        "sggNm": "광진구",
        "umdNm": "구의동",
        "jimok": "대",
        "jibun": "2**",
        "dealAmount": "17,500",
        "dealArea": "11.4",
        "dealingGbn": "중개거래",
        "landUse": "제3종일반주거지역",
        "shareDealingType": null,
        "cdealType": null,
        "cdealDay": null,
        "estateAgentSggNm": "서울 강남구",
        "dealYear": "2022",
        "dealMonth": "5",
        "dealDay": "23"
      },
      {
        "sggCd": "11215",
        "sggNm": "광진구",
        "umdNm": "자양동",
        "jimok": "도로",
        "jibun": "*",
        "dealAmount": "65,000",
        "dealArea": "35",
        "dealingGbn": "중개거래",
        "landUse": "제2종일반주거지역",
        "shareDealingType": null,
        "cdealType": "O",
        "cdealDay": "22.08.30",
        "estateAgentSggNm": "서울 광진구",
        "dealYear": "2022",
        "dealMonth": "5",
        "dealDay": "10"
      },
      {
        "sggCd": "11215",
        "sggNm": "광진구",
        "umdNm": "중곡동",
        "jimok": "임야",
        "jibun": "1**",
        "dealAmount": "1,077",
        "dealArea": "99.17",
        "dealingGbn": "직거래",
        "landUse": "개발제한구역",
        "shareDealingType": "지분",
        "cdealType": null,
        "cdealDay": null,
        "estateAgentSggNm": null,
        "dealYear": "2022",
        "dealMonth": "5",
        "dealDay": "2"
      },
      {
        "sggCd": "11215",
        "sggNm": "광진구",
        "umdNm": "구의동",
        "jimok": "대",
        "jibun": "2**",
        "dealAmount": "3,600",
        "dealArea": "5.3",
        "dealingGbn": "직거래",
        "landUse": "제3종일반주거지역",
        "shareDealingType": null,
        "cdealType": null,
        "cdealDay": null,
        "estateAgentSggNm": null,
        "dealYear": "2022",
        "dealMonth": "5",
        "dealDay": "13"
      },
      {
        "sggCd": "11215",
        "sggNm": "광진구",
        "umdNm": "구의동",
        "jimok": "도로",
        "jibun": "2**",
        "dealAmount": "45,030",
        "dealArea": "113.7",
        "dealingGbn": "직거래",
        "landUse": "준주거지역",
        "shareDealingType": null,
        "cdealType": null,
        "cdealDay": null,
        "estateAgentSggNm": null,
        "dealYear": "2022",
        "dealMonth": "5",
        "dealDay": "13"
      },
      {
        "sggCd": "11215",
        "sggNm": "광진구",
        "umdNm": "구의동",
        "jimok": "도로",
        "jibun": "2**",
        "dealAmount": "6,370",
        "dealArea": "24.5",
        "dealingGbn": "직거래",
        "landUse": "제3종일반주거지역",
        "shareDealingType": null,
        "cdealType": null,
        "cdealDay": null,
        "estateAgentSggNm": null,
        "dealYear": "2022",
        "dealMonth": "5",
        "dealDay": "13"
      },
      {
        "sggCd": "11215",
        "sggNm": "광진구",
        "umdNm": "자양동",
        "jimok": "대",
        "jibun": "5**",
        "dealAmount": "5,965",
        "dealArea": "5.96",
        "dealingGbn": "중개거래",
        "landUse": "준주거지역",
        "shareDealingType": "지분",
        "cdealType": null,
        "cdealDay": null,
        "estateAgentSggNm": "서울 광진구",
        "dealYear": "2022",
        "dealMonth": "5",
        "dealDay": "16"
      }
    ]
  },
  {
    "lawd_cd": "11215",
    "deal_ymd": "202206",
    "total_count": 11,
    "items": [
      {
        "sggCd": "11215",
        "sggNm": "광진구",
        "umdNm": "광장동",
        "jimok": "임야",
        "jibun": "2**",
        "dealAmount": "400",
        "dealArea": "7.57",
        "dealingGbn": "직거래",
        "landUse": "제1종일반주거지역",
        "shareDealingType": "지분",
        "cdealType": null,
        "cdealDay": null,
        "estateAgentSggNm": null,
        "dealYear": "2022",
        "dealMonth": "6",
        "dealDay": "9"
      },
      {
        "sggCd": "11215",
        "sggNm": "광진구",
        "umdNm": "자양동",
        "jimok": "대",
        "jibun": "6**",
        "dealAmount": "400,000",
        "dealArea": "112.6",
        "dealingGbn": "직거래",
        "landUse": "준주거지역",
        "shareDealingType": null,
        "cdealType": null,
        "cdealDay": null,
        "estateAgentSggNm": null,
        "dealYear": "2022",
        "dealMonth": "6",
        "dealDay": "20"
      },
      {
        "sggCd": "11215",
        "sggNm": "광진구",
        "umdNm": "자양동",
        "jimok": "도로",
        "jibun": "5**",
        "dealAmount": "182,873",
        "dealArea": "555",
        "dealingGbn": "직거래",
        "landUse": "제2종일반주거지역",
        "shareDealingType": null,
        "cdealType": null,
        "cdealDay": null,
        "estateAgentSggNm": null,
        "dealYear": "2022",
        "dealMonth": "6",
        "dealDay": "20"
      },
      {
        "sggCd": "11215",
        "sggNm": "광진구",
        "umdNm": "자양동",
        "jimok": "도로",
        "jibun": "5**",
        "dealAmount": "26,031",
        "dealArea": "79",
        "dealingGbn": "직거래",
        "landUse": "제2종일반주거지역",
        "shareDealingType": null,
        "cdealType": null,
        "cdealDay": null,
        "estateAgentSggNm": null,
        "dealYear": "2022",
        "dealMonth": "6",
        "dealDay": "20"
      },
      {
        "sggCd": "11215",
        "sggNm": "광진구",
        "umdNm": "중곡동",
        "jimok": "임야",
        "jibun": "7*",
        "dealAmount": "500",
        "dealArea": "22.5",
        "dealingGbn": "직거래",
        "landUse": "개발제한구역",
        "shareDealingType": "지분",
        "cdealType": null,
        "cdealDay": null,
        "estateAgentSggNm": null,
        "dealYear": "2022",
        "dealMonth": "6",
        "dealDay": "2"
      },
      {
        "sggCd": "11215",
        "sggNm": "광진구",
        "umdNm": "중곡동",
        "jimok": "임야",
        "jibun": "7*",
        "dealAmount": "800",
        "dealArea": "46.2",
        "dealingGbn": "직거래",
        "landUse": "개발제한구역",
        "shareDealingType": "지분",
        "cdealType": null,
        "cdealDay": null,
        "estateAgentSggNm": null,
        "dealYear": "2022",
        "dealMonth": "6",
        "dealDay": "2"
      },
      {
        "sggCd": "11215",
        "sggNm": "광진구",
        "umdNm": "중곡동",
        "jimok": "임야",
        "jibun": "7*",
        "dealAmount": "1,000",
        "dealArea": "10.4",
        "dealingGbn": "직거래",
        "landUse": "개발제한구역",
        "shareDealingType": "지분",
        "cdealType": null,
        "cdealDay": null,
        "estateAgentSggNm": null,
        "dealYear": "2022",
        "dealMonth": "6",
        "dealDay": "2"
      },
      {
        "sggCd": "11215",
        "sggNm": "광진구",
        "umdNm": "중곡동",
        "jimok": "임야",
        "jibun": "7*",
        "dealAmount": "500",
        "dealArea": "5.8",
        "dealingGbn": "직거래",
        "landUse": "개발제한구역",
        "shareDealingType": "지분",
        "cdealType": null,
        "cdealDay": null,
        "estateAgentSggNm": null,
        "dealYear": "2022",
        "dealMonth": "6",
        "dealDay": "2"
      },
      {
        "sggCd": "11215",
        "sggNm": "광진구",
        "umdNm": "중곡동",
        "jimok": "임야",
        "jibun": "7*",
        "dealAmount": "200",
        "dealArea": "1.8",
        "dealingGbn": "직거래",
        "landUse": "자연녹지지역",
        "shareDealingType": "지분",
        "cdealType": null,
        "cdealDay": null,
        "estateAgentSggNm": null,
        "dealYear": "2022",
        "dealMonth": "6",
        "dealDay": "2"
      },
      {
        "sggCd": "11215",
        "sggNm": "광진구",
        "umdNm": "중곡동",
        "jimok": "임야",
        "jibun": "1**",
        "dealAmount": "8,000",
        "dealArea": "1104.1",
        "dealingGbn": "직거래",
        "landUse": "자연녹지지역",
        "shareDealingType": "지분",
        "cdealType": null,
        "cdealDay": null,
        "estateAgentSggNm": null,
        "dealYear": "2022",
        "dealMonth": "6",
        "dealDay": "2"
      },
      {
        "sggCd": "11215",
        "sggNm": "광진구",
        "umdNm": "중곡동",
        "jimok": "임야",
        "jibun": "1**",
        "dealAmount": "3,000",
        "dealArea": "689.7",
        "dealingGbn": "직거래",
        "landUse": "개발제한구역",
        "shareDealingType": "지분",
        "cdealType": null,
        "cdealDay": null,
        "estateAgentSggNm": null,
        "dealYear": "2022",
        "dealMonth": "6",
        "dealDay": "2"
      }
    ]
  },
  {
    "lawd_cd": "11215",
    "deal_ymd": "202207",
    "total_count": 3,
    "items": [
      {
        "sggCd": "11215",
        "sggNm": "광진구",
        "umdNm": "자양동",
        "jimok": "대",
        "jibun": "*",
        "dealAmount": "197,000",
        "dealArea": "104.1",
        "dealingGbn": "직거래",
        "landUse": "제2종일반주거지역",
        "shareDealingType": null,
        "cdealType": null,
        "cdealDay": null,
        "estateAgentSggNm": null,
        "dealYear": "2022",
        "dealMonth": "7",
        "dealDay": "18"
      },
      {
        "sggCd": "11215",
        "sggNm": "광진구",
        "umdNm": "자양동",
        "jimok": "대",
        "jibun": "*",
        "dealAmount": "197,000",
        "dealArea": "104.1",
        "dealingGbn": "직거래",
        "landUse": "제2종일반주거지역",
        "shareDealingType": null,
        "cdealType": null,
        "cdealDay": null,
        "estateAgentSggNm": null,
        "dealYear": "2022",
        "dealMonth": "7",
        "dealDay": "18"
      },
      {
        "sggCd": "11215",
        "sggNm": "광진구",
        "umdNm": "화양동",
        "jimok": "임야",
        "jibun": "9*",
        "dealAmount": "16,000",
        "dealArea": "13",
        "dealingGbn": "중개거래",
        "landUse": "준주거지역",
        "shareDealingType": null,
        "cdealType": null,
        "cdealDay": null,
        "estateAgentSggNm": "서울 광진구",
        "dealYear": "2022",
        "dealMonth": "7",
        "dealDay": "26"
      }
    ]
  },
  {
    "lawd_cd": "11215",
    "deal_ymd": "202208",
    "total_count": 5,
    "items": [
      {
        "sggCd": "11215",
        "sggNm": "광진구",
        "umdNm": "중곡동",
        "jimok": "임야",
        "jibun": "1**",
        "dealAmount": "2,545",
        "dealArea": "165.29",
        "dealingGbn": "직거래",
        "landUse": "개발제한구역",
        "shareDealingType": "지분",
        "cdealType": null,
        "cdealDay": null,
        "estateAgentSggNm": null,
        "dealYear": "2022",
        "dealMonth": "8",
        "dealDay": "26"
      },
      {
        "sggCd": "11215",
        "sggNm": "광진구",
        "umdNm": "구의동",
        "jimok": "도로",
        "jibun": "2**",
        "dealAmount": "20,000",
        "dealArea": "11.9",
        "dealingGbn": "중개거래",
        "landUse": "일반상업지역",
        "shareDealingType": null,
        "cdealType": null,
        "cdealDay": null,
        "estateAgentSggNm": "서울 광진구 서울 송파구",
        "dealYear": "2022",
        "dealMonth": "8",
        "dealDay": "19"
      },
      {
        "sggCd": "11215",
        "sggNm": "광진구",
        "umdNm": "자양동",
        "jimok": "도로",
        "jibun": "*",
        "dealAmount": "65,000",
        "dealArea": "35",
        "dealingGbn": "중개거래",
        "landUse": "제2종일반주거지역",
        "shareDealingType": null,
        "cdealType": null,
        "cdealDay": null,
        "estateAgentSggNm": "서울 광진구",
        "dealYear": "2022",
        "dealMonth": "8",
        "dealDay": "31"
      },
      {
        "sggCd": "11215",
        "sggNm": "광진구",
        "umdNm": "자양동",
        "jimok": "대",
        "jibun": "*",
        "dealAmount": "3,500",
        "dealArea": "4",
        "dealingGbn": "직거래",
        "landUse": "제2종일반주거지역",
        "shareDealingType": "지분",
        "cdealType": null,
        "cdealDay": null,
        "estateAgentSggNm": null,
        "dealYear": "2022",
        "dealMonth": "8",
        "dealDay": "5"
      },
      {
        "sggCd": "11215",
        "sggNm": "광진구",
        "umdNm": "자양동",
        "jimok": "대",
        "jibun": "*",
        "dealAmount": "3,500",
        "dealArea": "4",
        "dealingGbn": "직거래",
        "landUse": "제2종일반주거지역",
        "shareDealingType": "지분",
        "cdealType": null,
        "cdealDay": null,
        "estateAgentSggNm": null,
        "dealYear": "2022",
        "dealMonth": "8",
        "dealDay": "5"
      }
    ]
  },
  {
    "lawd_cd": "11215",
    "deal_ymd": "202209",
    "total_count": 1,
    "items": [
      {
        "sggCd": "11215",
        "sggNm": "광진구",
        "umdNm": "능동",
        "jimok": "대",
        "jibun": "1**",
        "dealAmount": "2,166",
        "dealArea": "3",
        "dealingGbn": "직거래",
        "landUse": "제1종일반주거지역",
        "shareDealingType": null,
        "cdealType": null,
        "cdealDay": null,
        "estateAgentSggNm": null,
        "dealYear": "2022",
        "dealMonth": "9",
        "dealDay": "22"
      }
    ]
  },
  {
    "lawd_cd": "11215",
    "deal_ymd": "202210",
    "total_count": 4,
    "items": [
      {
        "sggCd": "11215",
        "sggNm": "광진구",
        "umdNm": "구의동",
        "jimok": "도로",
        "jibun": "2**",
        "dealAmount": "2,720",
        "dealArea": "6.61",
        "dealingGbn": "직거래",
        "landUse": "제2종일반주거지역",
        "shareDealingType": "지분",
        "cdealType": null,
        "cdealDay": null,
        "estateAgentSggNm": null,
        "dealYear": "2022",
        "dealMonth": "10",
        "dealDay": "26"
      },
      {
        "sggCd": "11215",
        "sggNm": "광진구",
        "umdNm": "구의동",
        "jimok": "도로",
        "jibun": "2**",
        "dealAmount": "1,360",
        "dealArea": "3.31",
        "dealingGbn": "직거래",
        "landUse": "제2종일반주거지역",
        "shareDealingType": "지분",
        "cdealType": null,
        "cdealDay": null,
        "estateAgentSggNm": null,
        "dealYear": "2022",
        "dealMonth": "10",
        "dealDay": "26"
      },
      {
        "sggCd": "11215",
        "sggNm": "광진구",
        "umdNm": "자양동",
        "jimok": "대",
        "jibun": "*",
        "dealAmount": "197,000",
        "dealArea": "104.1",
        "dealingGbn": "직거래",
        "landUse": "제2종일반주거지역",
        "shareDealingType": null,
        "cdealType": null,
        "cdealDay": null,
        "estateAgentSggNm": null,
        "dealYear": "2022",
        "dealMonth": "10",
        "dealDay": "14"
      },
      {
        "sggCd": "11215",
        "sggNm": "광진구",
        "umdNm": "자양동",
        "jimok": "대",
        "jibun": "*",
        "dealAmount": "197,000",
        "dealArea": "104.1",
        "dealingGbn": "직거래",
        "landUse": "제2종일반주거지역",
        "shareDealingType": null,
        "cdealType": null,
        "cdealDay": null,
        "estateAgentSggNm": null,
        "dealYear": "2022",
        "dealMonth": "10",
        "dealDay": "14"
      }
    ]
  },
  {
    "lawd_cd": "11215",
    "deal_ymd": "202211",
    "total_count": 13,
    "items": [
      {
        "sggCd": "11215",
        "sggNm": "광진구",
        "umdNm": "구의동",
        "jimok": "도로",
        "jibun": "2**",
        "dealAmount": "1,360",
        "dealArea": "3.31",
        "dealingGbn": "직거래",
        "landUse": "제2종일반주거지역",
        "shareDealingType": "지분",
        "cdealType": null,
        "cdealDay": null,
        "estateAgentSggNm": null,
        "dealYear": "2022",
        "dealMonth": "11",
        "dealDay": "30"
      },
      {
        "sggCd": "11215",
        "sggNm": "광진구",
        "umdNm": "구의동",
        "jimok": "도로",
        "jibun": "2**",
        "dealAmount": "4,500",
        "dealArea": "9.92",
        "dealingGbn": "직거래",
        "landUse": "제2종일반주거지역",
        "shareDealingType": "지분",
        "cdealType": null,
        "cdealDay": null,
        "estateAgentSggNm": null,
        "dealYear": "2022",
        "dealMonth": "11",
        "dealDay": "30"
      },
      {
        "sggCd": "11215",
        "sggNm": "광진구",
        "umdNm": "중곡동",
        "jimok": "도로",
        "jibun": "1**",
        "dealAmount": "2,670",
        "dealArea": "9.92",
        "dealingGbn": "직거래",
        "landUse": "제2종일반주거지역",
        "shareDealingType": "지분",
        "cdealType": null,
        "cdealDay": null,
        "estateAgentSggNm": null,
        "dealYear": "2022",
        "dealMonth": "11",
        "dealDay": "18"
      },
      {
        "sggCd": "11215",
        "sggNm": "광진구",
        "umdNm": "중곡동",
        "jimok": "도로",
        "jibun": "1**",
        "dealAmount": "1,780",
        "dealArea": "6.61",
        "dealingGbn": "직거래",
        "landUse": "제2종일반주거지역",
        "shareDealingType": "지분",
        "cdealType": null,
        "cdealDay": null,
        "estateAgentSggNm": null,
        "dealYear": "2022",
        "dealMonth": "11",
        "dealDay": "21"
      },
      {
        "sggCd": "11215",
        "sggNm": "광진구",
        "umdNm": "구의동",
        "jimok": "대",
        "jibun": "5**",
        "dealAmount": "15,720",
        "dealArea": "12",
        "dealingGbn": "직거래",
        "landUse": "제2종일반주거지역",
        "shareDealingType": null,
        "cdealType": null,
        "cdealDay": null,
        "estateAgentSggNm": null,
        "dealYear": "2022",
        "dealMonth": "11",
        "dealDay": "30"
      },
      {
        "sggCd": "11215",
        "sggNm": "광진구",
        "umdNm": "구의동",
        "jimok": "도로",
        "jibun": "2**",
        "dealAmount": "9,000",
        "dealArea": "19.83",
        "dealingGbn": "직거래",
        "landUse": "제2종일반주거지역",
        "shareDealingType": "지분",
        "cdealType": null,
        "cdealDay": null,
        "estateAgentSggNm": null,
        "dealYear": "2022",
        "dealMonth": "11",
        "dealDay": "16"
      },
      {
        "sggCd": "11215",
        "sggNm": "광진구",
        "umdNm": "구의동",
        "jimok": "도로",
        "jibun": "2**",
        "dealAmount": "1,360",
        "dealArea": "3.31",
        "dealingGbn": "직거래",
        "landUse": "제2종일반주거지역",
        "shareDealingType": "지분",
        "cdealType": null,
        "cdealDay": null,
        "estateAgentSggNm": null,
        "dealYear": "2022",
        "dealMonth": "11",
        "dealDay": "8"
      },
      {
        "sggCd": "11215",
        "sggNm": "광진구",
        "umdNm": "구의동",
        "jimok": "도로",
        "jibun": "2**",
        "dealAmount": "1,360",
        "dealArea": "3.31",
        "dealingGbn": "직거래",
        "landUse": "제2종일반주거지역",
        "shareDealingType": "지분",
        "cdealType": null,
        "cdealDay": null,
        "estateAgentSggNm": null,
        "dealYear": "2022",
        "dealMonth": "11",
        "dealDay": "1"
      },
      {
        "sggCd": "11215",
        "sggNm": "광진구",
        "umdNm": "구의동",
        "jimok": "도로",
        "jibun": "2**",
        "dealAmount": "1,360",
        "dealArea": "3.31",
        "dealingGbn": "직거래",
        "landUse": "제2종일반주거지역",
        "shareDealingType": "지분",
        "cdealType": null,
        "cdealDay": null,
        "estateAgentSggNm": null,
        "dealYear": "2022",
        "dealMonth": "11",
        "dealDay": "5"
      },
      {
        "sggCd": "11215",
        "sggNm": "광진구",
        "umdNm": "화양동",
        "jimok": "대",
        "jibun": "3*",
        "dealAmount": "146,000",
        "dealArea": "120.3",
        "dealingGbn": "직거래",
        "landUse": "제2종일반주거지역",
        "shareDealingType": null,
        "cdealType": null,
        "cdealDay": null,
        "estateAgentSggNm": null,
        "dealYear": "2022",
        "dealMonth": "11",
        "dealDay": "19"
      },
      {
        "sggCd": "11215",
        "sggNm": "광진구",
        "umdNm": "화양동",
        "jimok": "대",
        "jibun": "3*",
        "dealAmount": "146,000",
        "dealArea": "120.3",
        "dealingGbn": "직거래",
        "landUse": "제2종일반주거지역",
        "shareDealingType": null,
        "cdealType": null,
        "cdealDay": null,
        "estateAgentSggNm": null,
        "dealYear": "2022",
        "dealMonth": "11",
        "dealDay": "19"
      },
      {
        "sggCd": "11215",
        "sggNm": "광진구",
        "umdNm": "화양동",
        "jimok": "대",
        "jibun": "4**",
        "dealAmount": "15,125",
        "dealArea": "20",
        "dealingGbn": "직거래",
        "landUse": "제3종일반주거지역",
        "shareDealingType": null,
        "cdealType": null,
        "cdealDay": null,
        "estateAgentSggNm": null,
        "dealYear": "2022",
        "dealMonth": "11",
        "dealDay": "4"
      },
      {
        "sggCd": "11215",
        "sggNm": "광진구",
        "umdNm": "광장동",
        "jimok": "임야",
        "jibun": "2**",
        "dealAmount": "500",
        "dealArea": "7.57",
        "dealingGbn": "직거래",
        "landUse": "제1종일반주거지역",
        "shareDealingType": "지분",
        "cdealType": null,
        "cdealDay": null,
        "estateAgentSggNm": null,
        "dealYear": "2022",
        "dealMonth": "11",
        "dealDay": "1"
      }
    ]
  },
  {
    "lawd_cd": "11215",
    "deal_ymd": "202212",
    "total_count": 7,
    "items": [
      {
        "sggCd": "11215",
        "sggNm": "광진구",
        "umdNm": "중곡동",
        "jimok": "도로",
        "jibun": "1**",
        "dealAmount": "1,185",
        "dealArea": "3",
        "dealingGbn": "직거래",
        "landUse": "제2종일반주거지역",
        "shareDealingType": "지분",
        "cdealType": null,
        "cdealDay": null,
        "estateAgentSggNm": null,
        "dealYear": "2022",
        "dealMonth": "12",
        "dealDay": "20"
      },
      {
        "sggCd": "11215",
        "sggNm": "광진구",
        "umdNm": "중곡동",
        "jimok": "도로",
        "jibun": "1**",
        "dealAmount": "790",
        "dealArea": "2",
        "dealingGbn": "직거래",
        "landUse": "제2종일반주거지역",
        "shareDealingType": "지분",
        "cdealType": null,
        "cdealDay": null,
        "estateAgentSggNm": null,
        "dealYear": "2022",
        "dealMonth": "12",
        "dealDay": "22"
      },
      {
        "sggCd": "11215",
        "sggNm": "광진구",
        "umdNm": "중곡동",
        "jimok": "도로",
        "jibun": "1**",
        "dealAmount": "1,185",
        "dealArea": "3",
        "dealingGbn": "직거래",
        "landUse": "제2종일반주거지역",
        "shareDealingType": "지분",
        "cdealType": null,
        "cdealDay": null,
        "estateAgentSggNm": null,
        "dealYear": "2022",
        "dealMonth": "12",
        "dealDay": "14"
      },
      {
        "sggCd": "11215",
        "sggNm": "광진구",
        "umdNm": "중곡동",
        "jimok": "도로",
        "jibun": "1**",
        "dealAmount": "1,185",
        "dealArea": "3",
        "dealingGbn": "직거래",
        "landUse": "제2종일반주거지역",
        "shareDealingType": "지분",
        "cdealType": null,
        "cdealDay": null,
        "estateAgentSggNm": null,
        "dealYear": "2022",
        "dealMonth": "12",
        "dealDay": "13"
      },
      {
        "sggCd": "11215",
        "sggNm": "광진구",
        "umdNm": "중곡동",
        "jimok": "도로",
        "jibun": "1**",
        "dealAmount": "890",
        "dealArea": "3.31",
        "dealingGbn": "직거래",
        "landUse": "제2종일반주거지역",
        "shareDealingType": "지분",
        "cdealType": null,
        "cdealDay": null,
        "estateAgentSggNm": null,
        "dealYear": "2022",
        "dealMonth": "12",
        "dealDay": "19"
      },
      {
        "sggCd": "11215",
        "sggNm": "광진구",
        "umdNm": "구의동",
        "jimok": "도로",
        "jibun": "2**",
        "dealAmount": "1,500",
        "dealArea": "3.31",
        "dealingGbn": "직거래",
        "landUse": "제2종일반주거지역",
        "shareDealingType": "지분",
        "cdealType": null,
        "cdealDay": null,
        "estateAgentSggNm": null,
        "dealYear": "2022",
        "dealMonth": "12",
        "dealDay": "15"
      },
      {
        "sggCd": "11215",
        "sggNm": "광진구",
        "umdNm": "구의동",
        "jimok": "도로",
        "jibun": "2**",
        "dealAmount": "3,000",
        "dealArea": "6.61",
        "dealingGbn": "직거래",
        "landUse": "제2종일반주거지역",
        "shareDealingType": "지분",
        "cdealType": null,
        "cdealDay": null,
        "estateAgentSggNm": null,
        "dealYear": "2022",
        "dealMonth": "12",
        "dealDay": "1"
      }
    ]
  }
]